Workbook

Sheet Master 2026-2027 US Catalog
A1: EXHAUSTIVE MASTER VEHICLE DATABASE WITH REVIEWS, PROS, CONS & IMAGE URLS (USA 2026–2027)
A2: Enterprise master vehicle catalog (455 models) complete with full mechanical specs, Car and Driver ratings, pros, cons, editorial verdicts, and high-resolution image URLs.
A3: Year | B3: Make | C3: Model / Model Group | D3: Trim / Variant | E3: Body Type | F3: Fuel Type | G3: MSRP | H3: Horsepower | I3: Torque | J3: Engine | K3: Displacement | L3: Cylinders | M3: Transmission | N3: Drivetrain | O3: MPG | P3: EV range | Q3: Battery | R3: Seating | S3: Cargo | T3: Towing | U3: C&D Rating | V3: Pros (Highs) | W3: Cons (Lows) | X3: Review Summary / Verdict | Y3: Image URL | Z3: Review URL | AA3: C&D source
A4: 2026 | B4: Acura | C4: Integra | D4: A-Spec Tech 6MT | E4: Compact Liftback | F4: Gasoline | G4: 38000 | H4: 200 | I4: 192 | J4: 1.5L Turbo I4 | K4: 1.5 | L4: 4 | M4: 6-Speed Manual | N4: FWD | O4: 30 (26/36) | P4: N/A | Q4: N/A | R4: 5 | S4: 24.3 | T4: N/A | U4: 9.0/10 | V4: • Refined performance and chassis poise • Comfortable ergonomic cabin • Comprehensive safety suite | W4: • Firm ride on optional large wheels • Option packages add up quickly • Infotainment learning curve | X4: A solid, well-rounded contender in the US compact liftback class with competitive dynamics. | Y4: https://hips.hearstapps.com/hmg-prod/images/2026-acura-integra.jpg | Z4: https://www.caranddriver.com/acura/integra | AA4: Car and Driver 10Best
A5: 2026 | B5: Acura | C5: Integra | D5: Type S | E5: High-Performance Hatch | F5: Gasoline | G5: 53795 | H5: 320 | I5: 310 | J5: 2.0L Turbo VTEC I4 | K5: 2 | L5: 4 | M5: 6-Speed Manual | N5: FWD | O5: 24 (21/28) | P5: N/A | Q5: N/A | R5: 5 | S5: 24.3 | T5: N/A | U5: 10/10 | V5: • Refined performance and chassis poise • Comfortable ergonomic cabin • Comprehensive safety suite | W5: • Firm ride on optional large wheels • Option packages add up quickly • Infotainment learning curve | X5: A solid, well-rounded contender in the US high-performance hatch class with competitive dynamics. | Y5: https://hips.hearstapps.com/hmg-prod/images/2026-acura-integra.jpg | Z5: https://www.caranddriver.com/acura/integra-type-s | AA5: Car and Driver 10Best Winner
A6: 2026 | B6: Acura | C6: TLX | D6: Technology | E6: Compact Luxury Sedan | F6: Gasoline | G6: 46595 | H6: 272 | I6: 280 | J6: 2.0L Turbo I4 | K6: 2 | L6: 4 | M6: 10-Speed Auto | N6: FWD | O6: 25 (22/31) | P6: N/A | Q6: N/A | R6: 5 | S6: 13.5 | T6: N/A | U6: 8.0/10 | V6: • Sharper handling dynamics than taller SUVs • Superior highway fuel economy • Easy maneuvering in urban spaces | W6: • Less cargo flexibility than crossovers • Lower seating hip point for ingress • Fewer AWD options | X6: A well-proportioned compact luxury sedan offering superior driving manners and efficiency over conventional crossovers. | Y6: https://hips.hearstapps.com/hmg-prod/images/2026-acura-tlx.jpg | Z6: https://www.caranddriver.com/acura/tlx | AA6: Car and Driver Review
A7: 2026 | B7: Acura | C7: TLX | D7: Type S SH-AWD | E7: Sport Sedan | F7: Gasoline | G7: 58795 | H7: 355 | I7: 354 | J7: 3.0L Turbo V6 | K7: 3 | L7: 6 | M7: 10-Speed Auto | N7: SH-AWD | O7: 21 (19/25) | P7: N/A | Q7: N/A | R7: 5 | S7: 13.5 | T7: N/A | U7: 8.5/10 | V7: • Sharper handling dynamics than taller SUVs • Superior highway fuel economy • Easy maneuvering in urban spaces | W7: • Less cargo flexibility than crossovers • Lower seating hip point for ingress • Fewer AWD options | X7: A well-proportioned sport sedan offering superior driving manners and efficiency over conventional crossovers. | Y7: https://hips.hearstapps.com/hmg-prod/images/2026-acura-tlx.jpg | Z7: https://www.caranddriver.com/acura/tlx | AA7: Car and Driver Editors' Choice
A8: 2026 | B8: Acura | C8: RDX | D8: A-Spec Advance | E8: Compact Luxury Crossover | F8: Gasoline | G8: 55450 | H8: 272 | I8: 280 | J8: 2.0L Turbo I4 | K8: 2 | L8: 4 | M8: 10-Speed Auto | N8: SH-AWD | O8: 23 (21/26) | P8: N/A | Q8: N/A | R8: 5 | S8: 29.5 | T8: 1500 | U8: 8.0/10 | V8: • Spacious passenger and cargo room • Commanding elevated driving position • Confidence-inspiring all-weather grip | W8: • Higher center of gravity than sedans • Fuel consumption under heavy load • Less engaging steering feel | X8: A highly versatile compact luxury crossover that delivers generous space, modern safety tech, and daily utility. | Y8: https://hips.hearstapps.com/hmg-prod/images/2026-acura-rdx.jpg | Z8: https://www.caranddriver.com/acura/rdx | AA8: Car and Driver Buyer's Guide
A9: 2026 | B9: Acura | C9: MDX | D9: A-Spec Advance | E9: 3-Row Luxury SUV | F9: Gasoline | G9: 63000 | H9: 290 | I9: 267 | J9: 3.5L DOHC V6 | K9: 3.5 | L9: 6 | M9: 10-Speed Auto | N9: SH-AWD | O9: 21 (19/25) | P9: N/A | Q9: N/A | R9: 7 | S9: 16.3 | T9: 5000 | U9: 8.5/10 | V9: • Spacious passenger and cargo room • Commanding elevated driving position • Confidence-inspiring all-weather grip | W9: • Higher center of gravity than sedans • Fuel consumption under heavy load • Less engaging steering feel | X9: A highly versatile 3-row luxury suv that delivers generous space, modern safety tech, and daily utility. | Y9: https://hips.hearstapps.com/hmg-prod/images/2026-acura-mdx.jpg | Z9: https://www.caranddriver.com/acura/mdx | AA9: Car and Driver Buyer's Guide
A10: 2026 | B10: Acura | C10: MDX | D10: Type S Advance | E10: 3-Row Sport Luxury SUV | F10: Gasoline | G10: 76300 | H10: 355 | I10: 354 | J10: 3.0L Turbo V6 | K10: 3 | L10: 6 | M10: 10-Speed Auto | N10: SH-AWD | O10: 19 (17/21) | P10: N/A | Q10: N/A | R10: 7 | S10: 16.3 | T10: 5000 | U10: 8.5/10 | V10: • Spacious passenger and cargo room • Commanding elevated driving position • Confidence-inspiring all-weather grip | W10: • Higher center of gravity than sedans • Fuel consumption under heavy load • Less engaging steering feel | X10: A highly versatile 3-row sport luxury suv that delivers generous space, modern safety tech, and daily utility. | Y10: https://hips.hearstapps.com/hmg-prod/images/2026-acura-mdx.jpg | Z10: https://www.caranddriver.com/acura/mdx | AA10: Car and Driver Buyer's Guide
A11: 2026 | B11: Acura | C11: ZDX | D11: Type S | E11: Mid-Size Luxury EV SUV | F11: Electric | G11: 75895 | H11: 500 | I11: 544 | J11: Dual Electric Motors | K11: N/A | L11: 0 | M11: 1-Speed Direct-Drive | N11: AWD | O11: 79 MPGe | P11: 278 | Q11: 102 | R11: 5 | S11: 28.7 | T11: 3500 | U11: 8.0/10 | V11: • Silent, instantaneous acceleration • Low center of gravity enhances stability • Zero tailpipe emissions | W11: • Highway range drops at sustained speed • Public charging network variability • Pricier initial purchase cost | X11: A compelling electric entry in the mid-size luxury ev suv segment offering smooth power delivery and advanced tech. | Y11: https://hips.hearstapps.com/hmg-prod/images/2026-acura-zdx.jpg | Z11: https://www.caranddriver.com/acura/zdx | AA11: Car and Driver Buyer's Guide
A12: 2026 | B12: Alfa Romeo | C12: Giulia | D12: Veloce Q4 | E12: Compact Luxury Sedan | F12: Gasoline | G12: 48500 | H12: 280 | I12: 306 | J12: 2.0L Turbo I4 | K12: 2 | L12: 4 | M12: 8-Speed Auto | N12: AWD | O12: 26 (23/31) | P12: N/A | Q12: N/A | R12: 5 | S12: 13 | T12: N/A | U12: 8.5/10 | V12: • Sharper handling dynamics than taller SUVs • Superior highway fuel economy • Easy maneuvering in urban spaces | W12: • Less cargo flexibility than crossovers • Lower seating hip point for ingress • Fewer AWD options | X12: A well-proportioned compact luxury sedan offering superior driving manners and efficiency over conventional crossovers. | Y12: https://hips.hearstapps.com/hmg-prod/images/2026-alfa-romeo-giulia.jpg | Z12: https://www.caranddriver.com/alfa-romeo/giulia | AA12: Car and Driver Editors' Choice
A13: 2026 | B13: Alfa Romeo | C13: Giulia | D13: Quadrifoglio | E13: Sport Sedan | F13: Gasoline | G13: 83870 | H13: 505 | I13: 443 | J13: 2.9L Twin-Turbo V6 | K13: 2.9 | L13: 6 | M13: 8-Speed Auto | N13: RWD | O13: 20 (17/25) | P13: N/A | Q13: N/A | R13: 5 | S13: 13 | T13: N/A | U13: 9.5/10 | V13: • Sharper handling dynamics than taller SUVs • Superior highway fuel economy • Easy maneuvering in urban spaces | W13: • Less cargo flexibility than crossovers • Lower seating hip point for ingress • Fewer AWD options | X13: A well-proportioned sport sedan offering superior driving manners and efficiency over conventional crossovers. | Y13: https://hips.hearstapps.com/hmg-prod/images/2026-alfa-romeo-giulia.jpg | Z13: https://www.caranddriver.com/alfa-romeo/giulia-quadrifoglio | AA13: Car and Driver Editors' Choice
A14: 2026 | B14: Alfa Romeo | C14: Stelvio | D14: Quadrifoglio | E14: Sport Luxury SUV | F14: Gasoline | G14: 89870 | H14: 505 | I14: 443 | J14: 2.9L Twin-Turbo V6 | K14: 2.9 | L14: 6 | M14: 8-Speed Auto | N14: AWD | O14: 19 (17/23) | P14: N/A | Q14: N/A | R14: 5 | S14: 18.5 | T14: 3000 | U14: 9.0/10 | V14: • Spacious passenger and cargo room • Commanding elevated driving position • Confidence-inspiring all-weather grip | W14: • Higher center of gravity than sedans • Fuel consumption under heavy load • Less engaging steering feel | X14: A highly versatile sport luxury suv that delivers generous space, modern safety tech, and daily utility. | Y14: https://hips.hearstapps.com/hmg-prod/images/2026-alfa-romeo-stelvio.jpg | Z14: https://www.caranddriver.com/alfa-romeo/stelvio-quadrifoglio | AA14: Car and Driver Editors' Choice
A15: 2026 | B15: Alfa Romeo | C15: Tonale | D15: Veloce eAWD | E15: Subcompact Luxury Crossover | F15: PHEV | G15: 49590 | H15: 285 | I15: 347 | J15: 1.3L Turbo I4 + Motor | K15: 1.3 | L15: 4 | M15: 6-Speed Auto | N15: AWD | O15: 77 MPGe / 29 Comb | P15: 33 | Q15: 15.5 | R15: 5 | S15: 22.9 | T15: 2000 | U15: 8.0/10 | V15: • Superb real-world fuel economy • Smooth electric-gas power handover • No range anxiety on long trips | W15: • Added curb weight from battery packs • Slightly compromised cargo space • eCVT engine flare during passing | X15: A finely engineered phev subcompact luxury crossover striking the optimal balance between high efficiency and long-distance practicality. | Y15: https://hips.hearstapps.com/hmg-prod/images/2026-alfa-romeo-tonale.jpg | Z15: https://www.caranddriver.com/alfa-romeo/tonale | AA15: Car and Driver Buyer's Guide
A16: 2026 | B16: Aston Martin | C16: Vantage | D16: Coupe Base | E16: Grand Tourer Coupe | F16: Gasoline | G16: 194400 | H16: 656 | I16: 590 | J16: 4.0L Twin-Turbo V8 | K16: 4 | L16: 8 | M16: 8-Speed Auto (ZF) | N16: RWD | O16: 18 (15/22) | P16: N/A | Q16: N/A | R16: 2 | S16: 10 | T16: N/A | U16: 9.0/10 | V16: • Refined performance and chassis poise • Comfortable ergonomic cabin • Comprehensive safety suite | W16: • Firm ride on optional large wheels • Option packages add up quickly • Infotainment learning curve | X16: A solid, well-rounded contender in the US grand tourer coupe class with competitive dynamics. | Y16: https://hips.hearstapps.com/hmg-prod/images/2026-aston-martin-vantage.jpg | Z16: https://www.caranddriver.com/aston-martin/vantage | AA16: Car and Driver First Drive
A17: 2026 | B17: Aston Martin | C17: DB12 | D17: Coupe Base | E17: Super Tourer | F17: Gasoline | G17: 250000 | H17: 671 | I17: 590 | J17: 4.0L Twin-Turbo V8 | K17: 4 | L17: 8 | M17: 8-Speed Auto | N17: RWD | O17: 17 (14/22) | P17: N/A | Q17: N/A | R17: 4 | S17: 9.2 | T17: N/A | U17: 9.0/10 | V17: • Refined performance and chassis poise • Comfortable ergonomic cabin • Comprehensive safety suite | W17: • Firm ride on optional large wheels • Option packages add up quickly • Infotainment learning curve | X17: A solid, well-rounded contender in the US super tourer class with competitive dynamics. | Y17: https://hips.hearstapps.com/hmg-prod/images/2026-aston-martin-db12.jpg | Z17: https://www.caranddriver.com/aston-martin/db12 | AA17: Car and Driver Review
A18: 2026 | B18: Aston Martin | C18: Vanquish | D18: Base V12 | E18: Flagship Super GT | F18: Gasoline | G18: 429000 | H18: 824 | I18: 738 | J18: 5.2L Twin-Turbo V12 | K18: 5.2 | L18: 12 | M18: 8-Speed Auto | N18: RWD | O18: 14 (12/18 Est) | P18: N/A | Q18: N/A | R18: 2 | S18: 8.8 | T18: N/A | U18: 9.5/10 | V18: • Refined performance and chassis poise • Comfortable ergonomic cabin • Comprehensive safety suite | W18: • Firm ride on optional large wheels • Option packages add up quickly • Infotainment learning curve | X18: A solid, well-rounded contender in the US flagship super gt class with competitive dynamics. | Y18: https://hips.hearstapps.com/hmg-prod/images/2026-aston-martin-vanquish.jpg | Z18: https://www.caranddriver.com/aston-martin/vanquish | AA18: Car and Driver First Look
A19: 2026 | B19: Aston Martin | C19: DBX | D19: DBX707 | E19: Ultra-Luxury SUV | F19: Gasoline | G19: 253000 | H19: 697 | I19: 663 | J19: 4.0L Twin-Turbo AMG V8 | K19: 4 | L19: 8 | M19: 9-Speed Wet-Clutch | N19: AWD | O19: 17 (15/20) | P19: N/A | Q19: N/A | R19: 5 | S19: 22.5 | T19: 5940 | U19: 9.0/10 | V19: • Spacious passenger and cargo room • Commanding elevated driving position • Confidence-inspiring all-weather grip | W19: • Higher center of gravity than sedans • Fuel consumption under heavy load • Less engaging steering feel | X19: A highly versatile ultra-luxury suv that delivers generous space, modern safety tech, and daily utility. | Y19: https://hips.hearstapps.com/hmg-prod/images/2026-aston-martin-dbx.jpg | Z19: https://www.caranddriver.com/aston-martin/dbx | AA19: Car and Driver Buyer's Guide
A20: 2026 | B20: Audi | C20: A3 | D20: Premium 40 TFSI | E20: Subcompact Luxury Sedan | F20: Mild Hybrid | G20: 40000 | H20: 201 | I20: 221 | J20: 2.0L Turbo I4 48V | K20: 2 | L20: 4 | M20: 7-Speed DSG | N20: AWD | O20: 30 (27/35) | P20: N/A | Q20: N/A | R20: 5 | S20: 10.9 | T20: N/A | U20: 9.0/10 | V20: • Superb real-world fuel economy • Smooth electric-gas power handover • No range anxiety on long trips | W20: • Added curb weight from battery packs • Slightly compromised cargo space • eCVT engine flare during passing | X20: A finely engineered mild hybrid subcompact luxury sedan striking the optimal balance between high efficiency and long-distance practicality. | Y20: https://hips.hearstapps.com/hmg-prod/images/2026-audi-a3.jpg | Z20: https://www.caranddriver.com/audi/a3 | AA20: Car and Driver Editors' Choice
A21: 2026 | B21: Audi | C21: S3 | D21: Premium Plus | E21: Sport Compact Sedan | F21: Gasoline | G21: 49500 | H21: 328 | I21: 310 | J21: 2.0L Turbo I4 | K21: 2 | L21: 4 | M21: 7-Speed DSG | N21: quattro AWD | O21: 26 (23/32) | P21: N/A | Q21: N/A | R21: 5 | S21: 8.3 | T21: N/A | U21: 9.0/10 | V21: • Sharper handling dynamics than taller SUVs • Superior highway fuel economy • Easy maneuvering in urban spaces | W21: • Less cargo flexibility than crossovers • Lower seating hip point for ingress • Fewer AWD options | X21: A well-proportioned sport compact sedan offering superior driving manners and efficiency over conventional crossovers. | Y21: https://hips.hearstapps.com/hmg-prod/images/2026-audi-s3.jpg | Z21: https://www.caranddriver.com/audi/s3 | AA21: Car and Driver Editors' Choice
A22: 2026 | B22: Audi | C22: RS3 | D22: Sedan Base | E22: High-Perf Compact Sedan | F22: Gasoline | G22: 63500 | H22: 401 | I22: 369 | J22: 2.5L Turbo Inline-5 | K22: 2.5 | L22: 5 | M22: 7-Speed DSG | N22: quattro AWD | O22: 23 (19/29) | P22: N/A | Q22: N/A | R22: 5 | S22: 8.3 | T22: N/A | U22: 9.5/10 | V22: • Sharper handling dynamics than taller SUVs • Superior highway fuel economy • Easy maneuvering in urban spaces | W22: • Less cargo flexibility than crossovers • Lower seating hip point for ingress • Fewer AWD options | X22: A well-proportioned high-perf compact sedan offering superior driving manners and efficiency over conventional crossovers. | Y22: https://hips.hearstapps.com/hmg-prod/images/2026-audi-rs3.jpg | Z22: https://www.caranddriver.com/audi/rs3 | AA22: Car and Driver 10Best
A23: 2026 | B23: Audi | C23: A5 | D23: Sedan Premium Plus | E23: Compact Executive Sedan | F23: Mild Hybrid | G23: 49000 | H23: 268 | I23: 295 | J23: 2.0L Turbo I4 48V | K23: 2 | L23: 4 | M23: 7-Speed Dual-Clutch | N23: quattro AWD | O23: 28 (24/33) | P23: N/A | Q23: N/A | R23: 5 | S23: 12 | T23: N/A | U23: 9.0/10 | V23: • Superb real-world fuel economy • Smooth electric-gas power handover • No range anxiety on long trips | W23: • Added curb weight from battery packs • Slightly compromised cargo space • eCVT engine flare during passing | X23: A finely engineered mild hybrid compact executive sedan striking the optimal balance between high efficiency and long-distance practicality. | Y23: https://hips.hearstapps.com/hmg-prod/images/2026-audi-a5.jpg | Z23: https://www.caranddriver.com/audi/a5 | AA23: Car and Driver First Look
A24: 2026 | B24: Audi | C24: S5 | D24: Sedan Prestige | E24: Sport Executive Sedan | F24: Mild Hybrid | G24: 64000 | H24: 362 | I24: 406 | J24: 3.0L Turbo V6 48V | K24: 3 | L24: 6 | M24: 7-Speed Dual-Clutch | N24: quattro AWD | O24: 24 (21/29) | P24: N/A | Q24: N/A | R24: 5 | S24: 12 | T24: N/A | U24: 9.0/10 | V24: • Superb real-world fuel economy • Smooth electric-gas power handover • No range anxiety on long trips | W24: • Added curb weight from battery packs • Slightly compromised cargo space • eCVT engine flare during passing | X24: A finely engineered mild hybrid sport executive sedan striking the optimal balance between high efficiency and long-distance practicality. | Y24: https://hips.hearstapps.com/hmg-prod/images/2026-audi-s5.jpg | Z24: https://www.caranddriver.com/audi/s5 | AA24: Car and Driver First Look
A25: 2026 | B25: Audi | C25: A6 | D25: 55 TFSI quattro | E25: Executive Sedan | F25: Mild Hybrid | G25: 62000 | H25: 335 | I25: 369 | J25: 3.0L Turbo V6 | K25: 3 | L25: 6 | M25: 7-Speed DSG | N25: quattro AWD | O25: 24 (21/30) | P25: N/A | Q25: N/A | R25: 5 | S25: 13.7 | T25: N/A | U25: 8.5/10 | V25: • Superb real-world fuel economy • Smooth electric-gas power handover • No range anxiety on long trips | W25: • Added curb weight from battery packs • Slightly compromised cargo space • eCVT engine flare during passing | X25: A finely engineered mild hybrid executive sedan striking the optimal balance between high efficiency and long-distance practicality. | Y25: https://hips.hearstapps.com/hmg-prod/images/2026-audi-a6.jpg | Z25: https://www.caranddriver.com/audi/a6 | AA25: Car and Driver Buyer's Guide
A26: 2026 | B26: Audi | C26: S6 | D26: Premium Plus | E26: Performance Sedan | F26: Mild Hybrid | G26: 76000 | H26: 444 | I26: 442 | J26: 2.9L Twin-Turbo V6 | K26: 2.9 | L26: 6 | M26: 8-Speed Auto | N26: quattro AWD | O26: 22 (19/26) | P26: N/A | Q26: N/A | R26: 5 | S26: 13.7 | T26: N/A | U26: 8.5/10 | V26: • Superb real-world fuel economy • Smooth electric-gas power handover • No range anxiety on long trips | W26: • Added curb weight from battery packs • Slightly compromised cargo space • eCVT engine flare during passing | X26: A finely engineered mild hybrid performance sedan striking the optimal balance between high efficiency and long-distance practicality. | Y26: https://hips.hearstapps.com/hmg-prod/images/2026-audi-s6.jpg | Z26: https://www.caranddriver.com/audi/s6 | AA26: Car and Driver Buyer's Guide
A27: 2026 | B27: Audi | C27: A6 e-tron | D27: Performance quattro | E27: Executive EV Sedan | F27: Electric | G27: 75000 | H27: 456 | I27: 520 | J27: Dual Electric Motors | K27: N/A | L27: 0 | M27: 1-Speed Direct | N27: quattro AWD | O27: 95 MPGe | P27: 380 | Q27: 100 | R27: 5 | S27: 18 | T27: N/A | U27: 9.0/10 | V27: • Silent, instantaneous acceleration • Low center of gravity enhances stability • Zero tailpipe emissions | W27: • Highway range drops at sustained speed • Public charging network variability • Pricier initial purchase cost | X27: A compelling electric entry in the executive ev sedan segment offering smooth power delivery and advanced tech. | Y27: https://hips.hearstapps.com/hmg-prod/images/2026-audi-a6-e-tron.jpg | Z27: https://www.caranddriver.com/audi/a6-e-tron | AA27: Car and Driver Preview
A28: 2026 | B28: Audi | C28: RS6 Avant | D28: Performance GT | E28: Performance Wagon | F28: Mild Hybrid | G28: 128895 | H28: 621 | I28: 627 | J28: 4.0L Twin-Turbo V8 | K28: 4 | L28: 8 | M28: 8-Speed Auto | N28: quattro AWD | O28: 17 (14/21) | P28: N/A | Q28: N/A | R28: 5 | S28: 30 | T28: N/A | U28: 10/10 | V28: • Superb real-world fuel economy • Smooth electric-gas power handover • No range anxiety on long trips | W28: • Added curb weight from battery packs • Slightly compromised cargo space • eCVT engine flare during passing | X28: A finely engineered mild hybrid performance wagon striking the optimal balance between high efficiency and long-distance practicality. | Y28: https://hips.hearstapps.com/hmg-prod/images/2026-audi-rs6-avant.jpg | Z28: https://www.caranddriver.com/audi/rs6-avant | AA28: Car and Driver 10Best
A29: 2026 | B29: Audi | C29: A7 | D29: 55 TFSI quattro | E29: Luxury Sportback | F29: Mild Hybrid | G29: 73000 | H29: 335 | I29: 369 | J29: 3.0L Turbo V6 | K29: 3 | L29: 6 | M29: 7-Speed DSG | N29: quattro AWD | O29: 24 (21/30) | P29: N/A | Q29: N/A | R29: 5 | S29: 24.9 | T29: N/A | U29: 9.0/10 | V29: • Superb real-world fuel economy • Smooth electric-gas power handover • No range anxiety on long trips | W29: • Added curb weight from battery packs • Slightly compromised cargo space • eCVT engine flare during passing | X29: A finely engineered mild hybrid luxury sportback striking the optimal balance between high efficiency and long-distance practicality. | Y29: https://hips.hearstapps.com/hmg-prod/images/2026-audi-a7.jpg | Z29: https://www.caranddriver.com/audi/a7 | AA29: Car and Driver Editors' Choice
A30: 2026 | B30: Audi | C30: RS7 | D30: Performance | E30: Super Sportback | F30: Mild Hybrid | G30: 129000 | H30: 621 | I30: 627 | J30: 4.0L Twin-Turbo V8 | K30: 4 | L30: 8 | M30: 8-Speed Auto | N30: quattro AWD | O30: 17 (14/21) | P30: N/A | Q30: N/A | R30: 5 | S30: 24.9 | T30: N/A | U30: 9.5/10 | V30: • Superb real-world fuel economy • Smooth electric-gas power handover • No range anxiety on long trips | W30: • Added curb weight from battery packs • Slightly compromised cargo space • eCVT engine flare during passing | X30: A finely engineered mild hybrid super sportback striking the optimal balance between high efficiency and long-distance practicality. | Y30: https://hips.hearstapps.com/hmg-prod/images/2026-audi-rs7.jpg | Z30: https://www.caranddriver.com/audi/rs7 | AA30: Car and Driver Editors' Choice
A31: 2026 | B31: Audi | C31: A8 | D31: 55 TFSI quattro | E31: Full-Size Luxury Flagship | F31: Mild Hybrid | G31: 92000 | H31: 335 | I31: 369 | J31: 3.0L Turbo V6 | K31: 3 | L31: 6 | M31: 8-Speed Auto | N31: quattro AWD | O31: 22 (19/28) | P31: N/A | Q31: N/A | R31: 5 | S31: 12.5 | T31: N/A | U31: 8.5/10 | V31: • Superb real-world fuel economy • Smooth electric-gas power handover • No range anxiety on long trips | W31: • Added curb weight from battery packs • Slightly compromised cargo space • eCVT engine flare during passing | X31: A finely engineered mild hybrid full-size luxury flagship striking the optimal balance between high efficiency and long-distance practicality. | Y31: https://hips.hearstapps.com/hmg-prod/images/2026-audi-a8.jpg | Z31: https://www.caranddriver.com/audi/a8 | AA31: Car and Driver Buyer's Guide
A32: 2026 | B32: Audi | C32: S8 | D32: Base | E32: Performance Flagship Sedan | F32: Mild Hybrid | G32: 126000 | H32: 563 | I32: 590 | J32: 4.0L Twin-Turbo V8 | K32: 4 | L32: 8 | M32: 8-Speed Auto | N32: quattro AWD | O32: 18 (15/24) | P32: N/A | Q32: N/A | R32: 5 | S32: 12.5 | T32: N/A | U32: 9.0/10 | V32: • Superb real-world fuel economy • Smooth electric-gas power handover • No range anxiety on long trips | W32: • Added curb weight from battery packs • Slightly compromised cargo space • eCVT engine flare during passing | X32: A finely engineered mild hybrid performance flagship sedan striking the optimal balance between high efficiency and long-distance practicality. | Y32: https://hips.hearstapps.com/hmg-prod/images/2026-audi-s8.jpg | Z32: https://www.caranddriver.com/audi/s8 | AA32: Car and Driver Editors' Choice
A33: 2026 | B33: Audi | C33: Q3 | D33: 45 TFSI Premium | E33: Subcompact Luxury Crossover | F33: Gasoline | G33: 42000 | H33: 228 | I33: 258 | J33: 2.0L Turbo I4 | K33: 2 | L33: 4 | M33: 8-Speed Auto | N33: quattro AWD | O33: 24 (21/28) | P33: N/A | Q33: N/A | R33: 5 | S33: 23.7 | T33: 2200 | U33: 8.0/10 | V33: • Spacious passenger and cargo room • Commanding elevated driving position • Confidence-inspiring all-weather grip | W33: • Higher center of gravity than sedans • Fuel consumption under heavy load • Less engaging steering feel | X33: A highly versatile subcompact luxury crossover that delivers generous space, modern safety tech, and daily utility. | Y33: https://hips.hearstapps.com/hmg-prod/images/2026-audi-q3.jpg | Z33: https://www.caranddriver.com/audi/q3 | AA33: Car and Driver Buyer's Guide
A34: 2026 | B34: Audi | C34: Q4 e-tron | D34: 55 quattro | E34: Compact EV SUV | F34: Electric | G34: 56500 | H34: 335 | I34: 402 | J34: Dual Electric Motors | K34: N/A | L34: 0 | M34: 1-Speed Direct | N34: quattro AWD | O34: 97 MPGe | P34: 258 | Q34: 82 | R34: 5 | S34: 24.8 | T34: 2600 | U34: 8.0/10 | V34: • Silent, instantaneous acceleration • Low center of gravity enhances stability • Zero tailpipe emissions | W34: • Highway range drops at sustained speed • Public charging network variability • Pricier initial purchase cost | X34: A compelling electric entry in the compact ev suv segment offering smooth power delivery and advanced tech. | Y34: https://hips.hearstapps.com/hmg-prod/images/2026-audi-q4-e-tron.jpg | Z34: https://www.caranddriver.com/audi/q4-e-tron | AA34: Car and Driver Buyer's Guide
A35: 2026 | B35: Audi | C35: Q5 | D35: 45 TFSI Premium | E35: Compact Luxury SUV | F35: Mild Hybrid | G35: 48000 | H35: 268 | I35: 295 | J35: 2.0L Turbo I4 | K35: 2 | L35: 4 | M35: 7-Speed DSG | N35: quattro AWD | O35: 26 (23/29) | P35: N/A | Q35: N/A | R35: 5 | S35: 25.8 | T35: 4400 | U35: 8.5/10 | V35: • Superb real-world fuel economy • Smooth electric-gas power handover • No range anxiety on long trips | W35: • Added curb weight from battery packs • Slightly compromised cargo space • eCVT engine flare during passing | X35: A finely engineered mild hybrid compact luxury suv striking the optimal balance between high efficiency and long-distance practicality. | Y35: https://hips.hearstapps.com/hmg-prod/images/2026-audi-q5.jpg | Z35: https://www.caranddriver.com/audi/q5 | AA35: Car and Driver Buyer's Guide
A36: 2026 | B36: Audi | C36: SQ5 | D36: Prestige | E36: Sport Compact SUV | F36: Mild Hybrid | G36: 66000 | H36: 362 | I36: 406 | J36: 3.0L Turbo V6 | K36: 3 | L36: 6 | M36: 7-Speed DSG | N36: quattro AWD | O36: 22 (19/25) | P36: N/A | Q36: N/A | R36: 5 | S36: 25.8 | T36: 4400 | U36: 8.5/10 | V36: • Superb real-world fuel economy • Smooth electric-gas power handover • No range anxiety on long trips | W36: • Added curb weight from battery packs • Slightly compromised cargo space • eCVT engine flare during passing | X36: A finely engineered mild hybrid sport compact suv striking the optimal balance between high efficiency and long-distance practicality. | Y36: https://hips.hearstapps.com/hmg-prod/images/2026-audi-sq5.jpg | Z36: https://www.caranddriver.com/audi/sq5 | AA36: Car and Driver Buyer's Guide
A37: 2026 | B37: Audi | C37: Q6 e-tron | D37: quattro Premium Plus | E37: Compact Luxury EV SUV | F37: Electric | G37: 67395 | H37: 456 | I37: 428 | J37: Dual Electric Motors | K37: N/A | L37: 0 | M37: 1-Speed Direct | N37: quattro AWD | O37: 90 MPGe | P37: 307 | Q37: 100 | R37: 5 | S37: 30.2 | T37: 4400 | U37: 9.0/10 | V37: • Silent, instantaneous acceleration • Low center of gravity enhances stability • Zero tailpipe emissions | W37: • Highway range drops at sustained speed • Public charging network variability • Pricier initial purchase cost | X37: A compelling electric entry in the compact luxury ev suv segment offering smooth power delivery and advanced tech. | Y37: https://hips.hearstapps.com/hmg-prod/images/2026-audi-q6-e-tron.jpg | Z37: https://www.caranddriver.com/audi/q6-e-tron | AA37: Car and Driver First Drive
A38: 2026 | B38: Audi | C38: Q7 | D38: 55 TFSI Prestige | E38: 3-Row Luxury SUV | F38: Mild Hybrid | G38: 69800 | H38: 335 | I38: 369 | J38: 3.0L Turbo V6 | K38: 3 | L38: 6 | M38: 8-Speed Auto | N38: quattro AWD | O38: 20 (18/23) | P38: N/A | Q38: N/A | R38: 7 | S38: 14.2 | T38: 7000 | U38: 8.5/10 | V38: • Superb real-world fuel economy • Smooth electric-gas power handover • No range anxiety on long trips | W38: • Added curb weight from battery packs • Slightly compromised cargo space • eCVT engine flare during passing | X38: A finely engineered mild hybrid 3-row luxury suv striking the optimal balance between high efficiency and long-distance practicality. | Y38: https://hips.hearstapps.com/hmg-prod/images/2026-audi-q7.jpg | Z38: https://www.caranddriver.com/audi/q7 | AA38: Car and Driver Buyer's Guide
A39: 2026 | B39: Audi | C39: Q8 | D39: 55 TFSI Prestige | E39: Mid-Size Luxury SUV | F39: Mild Hybrid | G39: 76000 | H39: 335 | I39: 369 | J39: 3.0L Turbo V6 | K39: 3 | L39: 6 | M39: 8-Speed Auto | N39: quattro AWD | O39: 19 (17/23) | P39: N/A | Q39: N/A | R39: 5 | S39: 30.5 | T39: 7700 | U39: 8.5/10 | V39: • Superb real-world fuel economy • Smooth electric-gas power handover • No range anxiety on long trips | W39: • Added curb weight from battery packs • Slightly compromised cargo space • eCVT engine flare during passing | X39: A finely engineered mild hybrid mid-size luxury suv striking the optimal balance between high efficiency and long-distance practicality. | Y39: https://hips.hearstapps.com/hmg-prod/images/2026-audi-q8.jpg | Z39: https://www.caranddriver.com/audi/q8 | AA39: Car and Driver Buyer's Guide
A40: 2026 | B40: Audi | C40: RS Q8 | D40: Performance | E40: Super SUV | F40: Mild Hybrid | G40: 137000 | H40: 631 | I40: 627 | J40: 4.0L Twin-Turbo V8 | K40: 4 | L40: 8 | M40: 8-Speed Auto | N40: quattro AWD | O40: 15 (13/19) | P40: N/A | Q40: N/A | R40: 5 | S40: 30.5 | T40: 7700 | U40: 9.0/10 | V40: • Superb real-world fuel economy • Smooth electric-gas power handover • No range anxiety on long trips | W40: • Added curb weight from battery packs • Slightly compromised cargo space • eCVT engine flare during passing | X40: A finely engineered mild hybrid super suv striking the optimal balance between high efficiency and long-distance practicality. | Y40: https://hips.hearstapps.com/hmg-prod/images/2026-audi-rs-q8.jpg | Z40: https://www.caranddriver.com/audi/rs-q8 | AA40: Car and Driver Editors' Choice
A41: 2026 | B41: Audi | C41: e-tron GT | D41: S e-tron GT | E41: Luxury EV Grand Tourer | F41: Electric | G41: 126000 | H41: 670 | I41: 612 | J41: Dual Electric Motors | K41: N/A | L41: 0 | M41: 2-Speed Rear / 1-Speed Front | N41: quattro AWD | O41: 85 MPGe | P41: 300 | Q41: 105 | R41: 4 | S41: 9.2 | T41: N/A | U41: 9.0/10 | V41: • Silent, instantaneous acceleration • Low center of gravity enhances stability • Zero tailpipe emissions | W41: • Highway range drops at sustained speed • Public charging network variability • Pricier initial purchase cost | X41: A compelling electric entry in the luxury ev grand tourer segment offering smooth power delivery and advanced tech. | Y41: https://hips.hearstapps.com/hmg-prod/images/2026-audi-e-tron-gt.jpg | Z41: https://www.caranddriver.com/audi/e-tron-gt | AA41: Car and Driver First Drive
A42: 2026 | B42: Bentley | C42: Continental GT | D42: Speed Ultra Hybrid | E42: Ultra-Luxury GT | F42: PHEV | G42: 305000 | H42: 771 | I42: 738 | J42: 4.0L Twin-Turbo V8 + Motor | K42: 4 | L42: 8 | M42: 8-Speed Dual-Clutch | N42: AWD | O42: 24 MPGe / 19 Comb | P42: 50 | Q42: 25.9 | R42: 4 | S42: 12.6 | T42: N/A | U42: 9.5/10 | V42: • Superb real-world fuel economy • Smooth electric-gas power handover • No range anxiety on long trips | W42: • Added curb weight from battery packs • Slightly compromised cargo space • eCVT engine flare during passing | X42: A finely engineered phev ultra-luxury gt striking the optimal balance between high efficiency and long-distance practicality. | Y42: https://hips.hearstapps.com/hmg-prod/images/2026-bentley-continental-gt.jpg | Z42: https://www.caranddriver.com/bentley/continental-gt | AA42: Car and Driver First Drive
A43: 2026 | B43: Bentley | C43: Flying Spur | D43: Speed PHEV | E43: Ultra-Luxury Sedan | F43: PHEV | G43: 318000 | H43: 771 | I43: 738 | J43: 4.0L Twin-Turbo V8 + Motor | K43: 4 | L43: 8 | M43: 8-Speed Dual-Clutch | N43: AWD | O43: 23 MPGe / 18 Comb | P43: 47 | Q43: 25.9 | R43: 5 | S43: 14.8 | T43: N/A | U43: 9.5/10 | V43: • Superb real-world fuel economy • Smooth electric-gas power handover • No range anxiety on long trips | W43: • Added curb weight from battery packs • Slightly compromised cargo space • eCVT engine flare during passing | X43: A finely engineered phev ultra-luxury sedan striking the optimal balance between high efficiency and long-distance practicality. | Y43: https://hips.hearstapps.com/hmg-prod/images/2026-bentley-flying-spur.jpg | Z43: https://www.caranddriver.com/bentley/flying-spur | AA43: Car and Driver Buyer's Guide
A44: 2026 | B44: Bentley | C44: Bentayga | D44: EWB Azure V8 | E44: Ultra-Luxury SUV | F44: Gasoline | G44: 240000 | H44: 542 | I44: 568 | J44: 4.0L Twin-Turbo V8 | K44: 4 | L44: 8 | M44: 8-Speed Auto | N44: AWD | O44: 17 (15/21) | P44: N/A | Q44: N/A | R44: 5 | S44: 17.1 | T44: 7716 | U44: 9.0/10 | V44: • Spacious passenger and cargo room • Commanding elevated driving position • Confidence-inspiring all-weather grip | W44: • Higher center of gravity than sedans • Fuel consumption under heavy load • Less engaging steering feel | X44: A highly versatile ultra-luxury suv that delivers generous space, modern safety tech, and daily utility. | Y44: https://hips.hearstapps.com/hmg-prod/images/2026-bentley-bentayga.jpg | Z44: https://www.caranddriver.com/bentley/bentayga | AA44: Car and Driver Buyer's Guide
A45: 2026 | B45: BMW | C45: 2-Series Coupe | D45: M240i xDrive | E45: Compact Sport Coupe | F45: Gasoline | G45: 52500 | H45: 382 | I45: 369 | J45: 3.0L Turbo I6 (B58) | K45: 3 | L45: 6 | M45: 8-Speed Sport Auto | N45: AWD | O45: 26 (23/32) | P45: N/A | Q45: N/A | R45: 4 | S45: 10 | T45: N/A | U45: 9.5/10 | V45: • Refined performance and chassis poise • Comfortable ergonomic cabin • Comprehensive safety suite | W45: • Firm ride on optional large wheels • Option packages add up quickly • Infotainment learning curve | X45: A solid, well-rounded contender in the US compact sport coupe class with competitive dynamics. | Y45: https://hips.hearstapps.com/hmg-prod/images/2026-bmw-2-series-coupe.jpg | Z45: https://www.caranddriver.com/bmw/2-series | AA45: Car and Driver 10Best
A46: 2026 | B46: BMW | C46: M2 | D46: Coupe 6MT | E46: Performance Sport Coupe | F46: Gasoline | G46: 66075 | H46: 473 | I46: 406 | J46: 3.0L Twin-Turbo I6 (S58) | K46: 3 | L46: 6 | M46: 6-Speed Manual | N46: RWD | O46: 19 (16/24) | P46: N/A | Q46: N/A | R46: 4 | S46: 13.8 | T46: N/A | U46: 10/10 | V46: • Explosive twin-turbo S58 inline-6 power • Razor-sharp chassis tuning • Manual still available on key trims | W46: • Polarizing front styling • Numb steering on-center feel • Option packages escalate price rapidly | X46: Relentlessly capable performance icons that deliver brutal track capability and executive prestige. | Y46: https://hips.hearstapps.com/hmg-prod/images/2026-bmw-m2.jpg | Z46: https://www.caranddriver.com/bmw/m2 | AA46: Car and Driver 10Best Winner
A47: 2026 | B47: BMW | C47: 3-Series | D47: 330i xDrive | E47: Compact Sport Sedan | F47: Mild Hybrid | G47: 48500 | H47: 255 | I47: 295 | J47: 2.0L Turbo I4 | K47: 2 | L47: 4 | M47: 8-Speed Sport Auto | N47: AWD | O47: 28 (24/33) | P47: N/A | Q47: N/A | R47: 5 | S47: 17 | T47: N/A | U47: 9.5/10 | V47: • Superb real-world fuel economy • Smooth electric-gas power handover • No range anxiety on long trips | W47: • Added curb weight from battery packs • Slightly compromised cargo space • eCVT engine flare during passing | X47: A finely engineered mild hybrid compact sport sedan striking the optimal balance between high efficiency and long-distance practicality. | Y47: https://hips.hearstapps.com/hmg-prod/images/2026-bmw-3-series.jpg | Z47: https://www.caranddriver.com/bmw/3-series | AA47: Car and Driver 10Best
A48: 2026 | B48: BMW | C48: 3-Series / M340i | D48: M340i xDrive | E48: Compact Sport Sedan | F48: Mild Hybrid | G48: 61775 | H48: 386 | I48: 398 | J48: 3.0L Turbo I6 (B58) | K48: 3 | L48: 6 | M48: 8-Speed Sport Auto | N48: AWD | O48: 26 (23/31) | P48: N/A | Q48: N/A | R48: 5 | S48: 17 | T48: N/A | U48: 10/10 | V48: • Explosive twin-turbo S58 inline-6 power • Razor-sharp chassis tuning • Manual still available on key trims | W48: • Polarizing front styling • Numb steering on-center feel • Option packages escalate price rapidly | X48: Relentlessly capable performance icons that deliver brutal track capability and executive prestige. | Y48: https://hips.hearstapps.com/hmg-prod/images/2026-bmw-3-series-m340i.jpg | Z48: https://www.caranddriver.com/bmw/3-series | AA48: Car and Driver 10Best Winner
A49: 2026 | B49: BMW | C49: M3 | D49: Competition xDrive | E49: High-Performance Sedan | F49: Gasoline | G49: 86300 | H49: 523 | I49: 479 | J49: 3.0L Twin-Turbo I6 (S58) | K49: 3 | L49: 6 | M49: 8-Speed M Steptronic | N49: M xDrive AWD | O49: 18 (16/22) | P49: N/A | Q49: N/A | R49: 5 | S49: 13 | T49: N/A | U49: 10/10 | V49: • Explosive twin-turbo S58 inline-6 power • Razor-sharp chassis tuning • Manual still available on key trims | W49: • Polarizing front styling • Numb steering on-center feel • Option packages escalate price rapidly | X49: Relentlessly capable performance icons that deliver brutal track capability and executive prestige. | Y49: https://hips.hearstapps.com/hmg-prod/images/2026-bmw-m3.jpg | Z49: https://www.caranddriver.com/bmw/m3 | AA49: Car and Driver 10Best Winner
A50: 2026 | B50: BMW | C50: 4-Series | D50: 430i Gran Coupe | E50: Compact 4-Door Coupe | F50: Mild Hybrid | G50: 50000 | H50: 255 | I50: 295 | J50: 2.0L Turbo I4 | K50: 2 | L50: 4 | M50: 8-Speed Sport Auto | N50: RWD | O50: 28 (25/34) | P50: N/A | Q50: N/A | R50: 5 | S50: 16.6 | T50: N/A | U50: 9.0/10 | V50: • Superb real-world fuel economy • Smooth electric-gas power handover • No range anxiety on long trips | W50: • Added curb weight from battery packs • Slightly compromised cargo space • eCVT engine flare during passing | X50: A finely engineered mild hybrid compact 4-door coupe striking the optimal balance between high efficiency and long-distance practicality. | Y50: https://hips.hearstapps.com/hmg-prod/images/2026-bmw-4-series.jpg | Z50: https://www.caranddriver.com/bmw/4-series | AA50: Car and Driver Editors' Choice
A51: 2026 | B51: BMW | C51: M4 | D51: Competition xDrive Coupe | E51: High-Performance Coupe | F51: Gasoline | G51: 89300 | H51: 523 | I51: 479 | J51: 3.0L Twin-Turbo I6 (S58) | K51: 3 | L51: 6 | M51: 8-Speed M Steptronic | N51: M xDrive AWD | O51: 18 (16/22) | P51: N/A | Q51: N/A | R51: 4 | S51: 12 | T51: N/A | U51: 9.5/10 | V51: • Explosive twin-turbo S58 inline-6 power • Razor-sharp chassis tuning • Manual still available on key trims | W51: • Polarizing front styling • Numb steering on-center feel • Option packages escalate price rapidly | X51: Relentlessly capable performance icons that deliver brutal track capability and executive prestige. | Y51: https://hips.hearstapps.com/hmg-prod/images/2026-bmw-m4.jpg | Z51: https://www.caranddriver.com/bmw/m4 | AA51: Car and Driver Editors' Choice
A52: 2026 | B52: BMW | C52: i4 | D52: eDrive40 Gran Coupe | E52: Compact EV Sedan | F52: Electric | G52: 59075 | H52: 335 | I52: 317 | J52: Rear Electric Motor | K52: N/A | L52: 0 | M52: 1-Speed Direct | N52: RWD | O52: 109 MPGe | P52: 318 | Q52: 84.3 | R52: 5 | S52: 10 | T52: N/A | U52: 9.0/10 | V52: • Silent, instantaneous acceleration • Low center of gravity enhances stability • Zero tailpipe emissions | W52: • Highway range drops at sustained speed • Public charging network variability • Pricier initial purchase cost | X52: A compelling electric entry in the compact ev sedan segment offering smooth power delivery and advanced tech. | Y52: https://hips.hearstapps.com/hmg-prod/images/2026-bmw-i4.jpg | Z52: https://www.caranddriver.com/bmw/i4 | AA52: Car and Driver 10Best
A53: 2026 | B53: BMW | C53: i4 | D53: M50 xDrive | E53: Performance EV Sedan | F53: Electric | G53: 71000 | H53: 536 | I53: 586 | J53: Dual Electric Motors | K53: N/A | L53: 0 | M53: 1-Speed Direct | N53: AWD | O53: 95 MPGe | P53: 269 | Q53: 84.3 | R53: 5 | S53: 10 | T53: N/A | U53: 9.0/10 | V53: • Silent, instantaneous acceleration • Low center of gravity enhances stability • Zero tailpipe emissions | W53: • Highway range drops at sustained speed • Public charging network variability • Pricier initial purchase cost | X53: A compelling electric entry in the performance ev sedan segment offering smooth power delivery and advanced tech. | Y53: https://hips.hearstapps.com/hmg-prod/images/2026-bmw-i4.jpg | Z53: https://www.caranddriver.com/bmw/i4 | AA53: Car and Driver Editors' Choice
A54: 2026 | B54: BMW | C54: 5-Series | D54: 540i xDrive | E54: Executive Luxury Sedan | F54: Mild Hybrid | G54: 66500 | H54: 375 | I54: 398 | J54: 3.0L Turbo I6 48V | K54: 3 | L54: 6 | M54: 8-Speed Steptronic | N54: xDrive AWD | O54: 28 (26/33) | P54: N/A | Q54: N/A | R54: 5 | S54: 18.4 | T54: N/A | U54: 9.0/10 | V54: • Superb real-world fuel economy • Smooth electric-gas power handover • No range anxiety on long trips | W54: • Added curb weight from battery packs • Slightly compromised cargo space • eCVT engine flare during passing | X54: A finely engineered mild hybrid executive luxury sedan striking the optimal balance between high efficiency and long-distance practicality. | Y54: https://hips.hearstapps.com/hmg-prod/images/2026-bmw-5-series.jpg | Z54: https://www.caranddriver.com/bmw/5-series | AA54: Car and Driver Editors' Choice
A55: 2026 | B55: BMW | C55: M5 | D55: Sedan Base | E55: High-Performance Sedan | F55: PHEV | G55: 120675 | H55: 717 | I55: 738 | J55: 4.4L Twin-Turbo V8 + Motor | K55: 4.4 | L55: 8 | M55: 8-Speed M Steptronic | N55: M xDrive AWD | O55: 22 MPGe / 17 Comb | P55: 25 | Q55: 14.8 | R55: 5 | S55: 16.5 | T55: N/A | U55: 9.0/10 | V55: • Superb real-world fuel economy • Smooth electric-gas power handover • No range anxiety on long trips | W55: • Added curb weight from battery packs • Slightly compromised cargo space • eCVT engine flare during passing | X55: A finely engineered phev high-performance sedan striking the optimal balance between high efficiency and long-distance practicality. | Y55: https://hips.hearstapps.com/hmg-prod/images/2026-bmw-m5.jpg | Z55: https://www.caranddriver.com/bmw/m5 | AA55: Car and Driver Tested
A56: 2026 | B56: BMW | C56: 7-Series | D56: 760i xDrive | E56: Full-Size Luxury Sedan | F56: Mild Hybrid | G56: 122500 | H56: 536 | I56: 553 | J56: 4.4L Twin-Turbo V8 | K56: 4.4 | L56: 8 | M56: 8-Speed Auto | N56: xDrive AWD | O56: 20 (18/25) | P56: N/A | Q56: N/A | R56: 5 | S56: 13.7 | T56: N/A | U56: 9.0/10 | V56: • Superb real-world fuel economy • Smooth electric-gas power handover • No range anxiety on long trips | W56: • Added curb weight from battery packs • Slightly compromised cargo space • eCVT engine flare during passing | X56: A finely engineered mild hybrid full-size luxury sedan striking the optimal balance between high efficiency and long-distance practicality. | Y56: https://hips.hearstapps.com/hmg-prod/images/2026-bmw-7-series.jpg | Z56: https://www.caranddriver.com/bmw/7-series | AA56: Car and Driver Editors' Choice
A57: 2026 | B57: BMW | C57: i7 | D57: M70 xDrive | E57: Ultra-Luxury Flagship EV | F57: Electric | G57: 169500 | H57: 650 | I57: 811 | J57: Dual Electric Motors | K57: N/A | L57: 0 | M57: 1-Speed Direct | N57: AWD | O57: 77 MPGe | P57: 291 | Q57: 105.7 | R57: 5 | S57: 11.4 | T57: N/A | U57: 9.0/10 | V57: • Silent, instantaneous acceleration • Low center of gravity enhances stability • Zero tailpipe emissions | W57: • Highway range drops at sustained speed • Public charging network variability • Pricier initial purchase cost | X57: A compelling electric entry in the ultra-luxury flagship ev segment offering smooth power delivery and advanced tech. | Y57: https://hips.hearstapps.com/hmg-prod/images/2026-bmw-i7.jpg | Z57: https://www.caranddriver.com/bmw/i7 | AA57: Car and Driver Review
A58: 2026 | B58: BMW | C58: 8-Series / M8 | D58: M8 Competition Gran Coupe | E58: Super Luxury 4-Door | F58: Gasoline | G58: 140000 | H58: 617 | I58: 553 | J58: 4.4L Twin-Turbo V8 | K58: 4.4 | L58: 8 | M58: 8-Speed M Steptronic | N58: M xDrive AWD | O58: 17 (15/22) | P58: N/A | Q58: N/A | R58: 5 | S58: 11 | T58: N/A | U58: 9.0/10 | V58: • Refined performance and chassis poise • Comfortable ergonomic cabin • Comprehensive safety suite | W58: • Firm ride on optional large wheels • Option packages add up quickly • Infotainment learning curve | X58: A solid, well-rounded contender in the US super luxury 4-door class with competitive dynamics. | Y58: https://hips.hearstapps.com/hmg-prod/images/2026-bmw-8-series-m8.jpg | Z58: https://www.caranddriver.com/bmw/m8-gran-coupe | AA58: Car and Driver Buyer's Guide
A59: 2026 | B59: BMW | C59: Z4 | D59: M40i Handschalter (6MT) | E59: Roadster | F59: Gasoline | G59: 71000 | H59: 382 | I59: 369 | J59: 3.0L Turbo I6 (B58) | K59: 3 | L59: 6 | M59: 6-Speed Manual | N59: RWD | O59: 26 (23/31) | P59: N/A | Q59: N/A | R59: 2 | S59: 9.9 | T59: N/A | U59: 9.5/10 | V59: • Refined performance and chassis poise • Comfortable ergonomic cabin • Comprehensive safety suite | W59: • Firm ride on optional large wheels • Option packages add up quickly • Infotainment learning curve | X59: A solid, well-rounded contender in the US roadster class with competitive dynamics. | Y59: https://hips.hearstapps.com/hmg-prod/images/2026-bmw-z4.jpg | Z59: https://www.caranddriver.com/bmw/z4 | AA59: Car and Driver Editors' Choice
A60: 2026 | B60: BMW | C60: X1 | D60: M35i xDrive | E60: Subcompact Sport SUV | F60: Gasoline | G60: 51000 | H60: 312 | I60: 295 | J60: 2.0L Turbo I4 | K60: 2 | L60: 4 | M60: 7-Speed Dual-Clutch | N60: xDrive AWD | O60: 26 (23/31) | P60: N/A | Q60: N/A | R60: 5 | S60: 25.7 | T60: 3500 | U60: 9.0/10 | V60: • Spacious passenger and cargo room • Commanding elevated driving position • Confidence-inspiring all-weather grip | W60: • Higher center of gravity than sedans • Fuel consumption under heavy load • Less engaging steering feel | X60: A highly versatile subcompact sport suv that delivers generous space, modern safety tech, and daily utility. | Y60: https://hips.hearstapps.com/hmg-prod/images/2026-bmw-x1.jpg | Z60: https://www.caranddriver.com/bmw/x1 | AA60: Car and Driver 10Best
A61: 2026 | B61: BMW | C61: X3 | D61: M50 xDrive | E61: Compact Luxury SUV | F61: Mild Hybrid | G61: 65275 | H61: 393 | I61: 428 | J61: 3.0L Turbo I6 48V | K61: 3 | L61: 6 | M61: 8-Speed Sport Auto | N61: xDrive AWD | O61: 27 (25/30) | P61: N/A | Q61: N/A | R61: 5 | S61: 31.5 | T61: 4850 | U61: 9.0/10 | V61: • Superb real-world fuel economy • Smooth electric-gas power handover • No range anxiety on long trips | W61: • Added curb weight from battery packs • Slightly compromised cargo space • eCVT engine flare during passing | X61: A finely engineered mild hybrid compact luxury suv striking the optimal balance between high efficiency and long-distance practicality. | Y61: https://hips.hearstapps.com/hmg-prod/images/2026-bmw-x3.jpg | Z61: https://www.caranddriver.com/bmw/x3 | AA61: Car and Driver Editors' Choice
A62: 2026 | B62: BMW | C62: X5 | D62: xDrive50e | E62: Mid-Size Luxury SUV | F62: PHEV | G62: 74275 | H62: 483 | I62: 516 | J62: 3.0L Turbo I6 + Motor | K62: 3 | L62: 6 | M62: 8-Speed Sport Auto | N62: xDrive AWD | O62: 58 MPGe / 22 Comb | P62: 38 | Q62: 25.7 | R62: 5 | S62: 33.1 | T62: 5952 | U62: 9.5/10 | V62: • Superb real-world fuel economy • Smooth electric-gas power handover • No range anxiety on long trips | W62: • Added curb weight from battery packs • Slightly compromised cargo space • eCVT engine flare during passing | X62: A finely engineered phev mid-size luxury suv striking the optimal balance between high efficiency and long-distance practicality. | Y62: https://hips.hearstapps.com/hmg-prod/images/2026-bmw-x5.jpg | Z62: https://www.caranddriver.com/bmw/x5 | AA62: Car and Driver 10Best Winner
A63: 2026 | B63: BMW | C63: X7 | D63: M60i xDrive | E63: 3-Row Flagship SUV | F63: Mild Hybrid | G63: 111900 | H63: 523 | I63: 553 | J63: 4.4L Twin-Turbo V8 | K63: 4.4 | L63: 8 | M63: 8-Speed Sport Auto | N63: xDrive AWD | O63: 18 (16/21) | P63: N/A | Q63: N/A | R63: 7 | S63: 12.8 | T63: 7500 | U63: 9.0/10 | V63: • Superb real-world fuel economy • Smooth electric-gas power handover • No range anxiety on long trips | W63: • Added curb weight from battery packs • Slightly compromised cargo space • eCVT engine flare during passing | X63: A finely engineered mild hybrid 3-row flagship suv striking the optimal balance between high efficiency and long-distance practicality. | Y63: https://hips.hearstapps.com/hmg-prod/images/2026-bmw-x7.jpg | Z63: https://www.caranddriver.com/bmw/x7 | AA63: Car and Driver Editors' Choice
A64: 2026 | B64: BMW | C64: iX | D64: xDrive50 | E64: Luxury EV SUV | F64: Electric | G64: 88500 | H64: 516 | I64: 564 | J64: Dual Electric Motors | K64: N/A | L64: 0 | M64: 1-Speed Direct | N64: AWD | O64: 83 MPGe | P64: 307 | Q64: 111.5 | R64: 5 | S64: 35.5 | T64: 5500 | U64: 9.0/10 | V64: • Silent, instantaneous acceleration • Low center of gravity enhances stability • Zero tailpipe emissions | W64: • Highway range drops at sustained speed • Public charging network variability • Pricier initial purchase cost | X64: A compelling electric entry in the luxury ev suv segment offering smooth power delivery and advanced tech. | Y64: https://hips.hearstapps.com/hmg-prod/images/2026-bmw-ix.jpg | Z64: https://www.caranddriver.com/bmw/ix | AA64: Car and Driver 10Best
A65: 2026 | B65: Buick | C65: Envista | D65: Avenir | E65: Subcompact Fastback | F65: Gasoline | G65: 30495 | H65: 137 | I65: 162 | J65: 1.2L Turbo I3 | K65: 1.2 | L65: 3 | M65: 6-Speed Auto | N65: FWD | O65: 30 (28/32) | P65: N/A | Q65: N/A | R65: 5 | S65: 20.7 | T65: N/A | U65: 8.5/10 | V65: • Refined performance and chassis poise • Comfortable ergonomic cabin • Comprehensive safety suite | W65: • Firm ride on optional large wheels • Option packages add up quickly • Infotainment learning curve | X65: A solid, well-rounded contender in the US subcompact fastback class with competitive dynamics. | Y65: https://hips.hearstapps.com/hmg-prod/images/2026-buick-envista.jpg | Z65: https://www.caranddriver.com/buick/envista | AA65: Car and Driver Editors' Choice
A66: 2026 | B66: Buick | C66: Encore GX | D66: Avenir AWD | E66: Subcompact Crossover | F66: Gasoline | G66: 34500 | H66: 155 | I66: 174 | J66: 1.3L Turbo I3 | K66: 1.3 | L66: 3 | M66: 9-Speed Auto | N66: AWD | O66: 27 (26/28) | P66: N/A | Q66: N/A | R66: 5 | S66: 23.5 | T66: 1000 | U66: 7.5/10 | V66: • Spacious passenger and cargo room • Commanding elevated driving position • Confidence-inspiring all-weather grip | W66: • Higher center of gravity than sedans • Fuel consumption under heavy load • Less engaging steering feel | X66: A highly versatile subcompact crossover that delivers generous space, modern safety tech, and daily utility. | Y66: https://hips.hearstapps.com/hmg-prod/images/2026-buick-encore-gx.jpg | Z66: https://www.caranddriver.com/buick/encore-gx | AA66: Car and Driver Buyer's Guide
A67: 2026 | B67: Buick | C67: Envision | D67: Avenir AWD | E67: Compact Premium SUV | F67: Gasoline | G67: 48000 | H67: 228 | I67: 258 | J67: 2.0L Turbo I4 | K67: 2 | L67: 4 | M67: 9-Speed Auto | N67: AWD | O67: 24 (21/28) | P67: N/A | Q67: N/A | R67: 5 | S67: 25.2 | T67: 1500 | U67: 8.0/10 | V67: • Spacious passenger and cargo room • Commanding elevated driving position • Confidence-inspiring all-weather grip | W67: • Higher center of gravity than sedans • Fuel consumption under heavy load • Less engaging steering feel | X67: A highly versatile compact premium suv that delivers generous space, modern safety tech, and daily utility. | Y67: https://hips.hearstapps.com/hmg-prod/images/2026-buick-envision.jpg | Z67: https://www.caranddriver.com/buick/envision | AA67: Car and Driver Buyer's Guide
A68: 2026 | B68: Buick | C68: Enclave | D68: Avenir AWD | E68: 3-Row Premium SUV | F68: Gasoline | G68: 59395 | H68: 328 | I68: 326 | J68: 2.5L Turbo I4 | K68: 2.5 | L68: 4 | M68: 8-Speed Auto | N68: AWD | O68: 21 (19/24) | P68: N/A | Q68: N/A | R68: 7 | S68: 22.9 | T68: 5000 | U68: 8.0/10 | V68: • Spacious passenger and cargo room • Commanding elevated driving position • Confidence-inspiring all-weather grip | W68: • Higher center of gravity than sedans • Fuel consumption under heavy load • Less engaging steering feel | X68: A highly versatile 3-row premium suv that delivers generous space, modern safety tech, and daily utility. | Y68: https://hips.hearstapps.com/hmg-prod/images/2026-buick-enclave.jpg | Z68: https://www.caranddriver.com/buick/enclave | AA68: Car and Driver Buyer's Guide
A69: 2026 | B69: Cadillac | C69: CT4 | D69: Premium Luxury AWD | E69: Compact Luxury Sedan | F69: Gasoline | G69: 43000 | H69: 310 | I69: 350 | J69: 2.7L Turbo Dual-Volute I4 | K69: 2.7 | L69: 4 | M69: 10-Speed Auto | N69: AWD | O69: 25 (22/31) | P69: N/A | Q69: N/A | R69: 5 | S69: 10.7 | T69: N/A | U69: 8.0/10 | V69: • Sharper handling dynamics than taller SUVs • Superior highway fuel economy • Easy maneuvering in urban spaces | W69: • Less cargo flexibility than crossovers • Lower seating hip point for ingress • Fewer AWD options | X69: A well-proportioned compact luxury sedan offering superior driving manners and efficiency over conventional crossovers. | Y69: https://hips.hearstapps.com/hmg-prod/images/2026-cadillac-ct4.jpg | Z69: https://www.caranddriver.com/cadillac/ct4 | AA69: Car and Driver Buyer's Guide
A70: 2026 | B70: Cadillac | C70: CT4-V Blackwing | D70: Base 6MT | E70: High-Perf Sport Sedan | F70: Gasoline | G70: 63590 | H70: 472 | I70: 445 | J70: 3.6L Twin-Turbo V6 | K70: 3.6 | L70: 6 | M70: 6-Speed Manual | N70: RWD | O70: 18 (15/23) | P70: N/A | Q70: N/A | R70: 5 | S70: 10.7 | T70: N/A | U70: 10/10 | V70: • Sharper handling dynamics than taller SUVs • Superior highway fuel economy • Easy maneuvering in urban spaces | W70: • Less cargo flexibility than crossovers • Lower seating hip point for ingress • Fewer AWD options | X70: A well-proportioned high-perf sport sedan offering superior driving manners and efficiency over conventional crossovers. | Y70: https://hips.hearstapps.com/hmg-prod/images/2026-cadillac-ct4-v-blackwing.jpg | Z70: https://www.caranddriver.com/cadillac/ct4-v-blackwing | AA70: Car and Driver 10Best Winner
A71: 2026 | B71: Cadillac | C71: CT5 | D71: Sport AWD | E71: Mid-Size Luxury Sedan | F71: Gasoline | G71: 49000 | H71: 335 | I71: 405 | J71: 3.0L Twin-Turbo V6 | K71: 3 | L71: 6 | M71: 10-Speed Auto | N71: AWD | O71: 21 (18/26) | P71: N/A | Q71: N/A | R71: 5 | S71: 11.9 | T71: N/A | U71: 8.5/10 | V71: • Sharper handling dynamics than taller SUVs • Superior highway fuel economy • Easy maneuvering in urban spaces | W71: • Less cargo flexibility than crossovers • Lower seating hip point for ingress • Fewer AWD options | X71: A well-proportioned mid-size luxury sedan offering superior driving manners and efficiency over conventional crossovers. | Y71: https://hips.hearstapps.com/hmg-prod/images/2026-cadillac-ct5.jpg | Z71: https://www.caranddriver.com/cadillac/ct5 | AA71: Car and Driver Buyer's Guide
A72: 2026 | B72: Cadillac | C72: CT5-V Blackwing | D72: Base 6MT | E72: Super Performance Sedan | F72: Gasoline | G72: 96990 | H72: 668 | I72: 659 | J72: 6.2L Supercharged LT4 V8 | K72: 6.2 | L72: 8 | M72: 6-Speed Manual | N72: RWD | O72: 15 (13/21) | P72: N/A | Q72: N/A | R72: 5 | S72: 11.9 | T72: N/A | U72: 10/10 | V72: • Sharper handling dynamics than taller SUVs • Superior highway fuel economy • Easy maneuvering in urban spaces | W72: • Less cargo flexibility than crossovers • Lower seating hip point for ingress • Fewer AWD options | X72: A well-proportioned super performance sedan offering superior driving manners and efficiency over conventional crossovers. | Y72: https://hips.hearstapps.com/hmg-prod/images/2026-cadillac-ct5-v-blackwing.jpg | Z72: https://www.caranddriver.com/cadillac/ct5-v-blackwing | AA72: Car and Driver 10Best Winner
A73: 2026 | B73: Cadillac | C73: Optiq | D73: Sport 1 AWD | E73: Compact Luxury EV SUV | F73: Electric | G73: 54390 | H73: 300 | I73: 354 | J73: Dual Ultium Electric Motors | K73: N/A | L73: 0 | M73: 1-Speed Direct | N73: eAWD | O73: 94 MPGe | P73: 302 | Q73: 85 | R73: 5 | S73: 26 | T73: 1500 | U73: 8.5/10 | V73: • Silent, instantaneous acceleration • Low center of gravity enhances stability • Zero tailpipe emissions | W73: • Highway range drops at sustained speed • Public charging network variability • Pricier initial purchase cost | X73: A compelling electric entry in the compact luxury ev suv segment offering smooth power delivery and advanced tech. | Y73: https://hips.hearstapps.com/hmg-prod/images/2026-cadillac-optiq.jpg | Z73: https://www.caranddriver.com/cadillac/optiq | AA73: Car and Driver First Drive
A74: 2026 | B74: Cadillac | C74: Lyriq | D74: Sport Dual-Motor AWD | E74: Mid-Size Luxury EV SUV | F74: Electric | G74: 63690 | H74: 500 | I74: 450 | J74: Dual Ultium Electric Motors | K74: N/A | L74: 0 | M74: 1-Speed Direct | N74: AWD | O74: 89 MPGe | P74: 303 | Q74: 102 | R74: 5 | S74: 28 | T74: 3500 | U74: 8.5/10 | V74: • Silent, instantaneous acceleration • Low center of gravity enhances stability • Zero tailpipe emissions | W74: • Highway range drops at sustained speed • Public charging network variability • Pricier initial purchase cost | X74: A compelling electric entry in the mid-size luxury ev suv segment offering smooth power delivery and advanced tech. | Y74: https://hips.hearstapps.com/hmg-prod/images/2026-cadillac-lyriq.jpg | Z74: https://www.caranddriver.com/cadillac/lyriq | AA74: Car and Driver Buyer's Guide
A75: 2026 | B75: Cadillac | C75: Vistiq | D75: Luxury AWD | E75: 3-Row Luxury EV SUV | F75: Electric | G75: 78790 | H75: 615 | I75: 650 | J75: Dual Permanent Magnet Motors | K75: N/A | L75: 0 | M75: 1-Speed Direct | N75: eAWD | O75: 78 MPGe | P75: 300 | Q75: 102 | R75: 7 | S75: 15.2 | T75: 5000 | U75: 9.0/10 | V75: • Silent, instantaneous acceleration • Low center of gravity enhances stability • Zero tailpipe emissions | W75: • Highway range drops at sustained speed • Public charging network variability • Pricier initial purchase cost | X75: A compelling electric entry in the 3-row luxury ev suv segment offering smooth power delivery and advanced tech. | Y75: https://hips.hearstapps.com/hmg-prod/images/2026-cadillac-vistiq.jpg | Z75: https://www.caranddriver.com/cadillac/vistiq | AA75: Car and Driver Buyer's Guide
A76: 2026 | B76: Cadillac | C76: Escalade | D76: V-Series 4WD | E76: Full-Size Performance SUV | F76: Gasoline | G76: 154290 | H76: 682 | I76: 653 | J76: 6.2L Supercharged V8 | K76: 6.2 | L76: 8 | M76: 10-Speed Auto | N76: AWD | O76: 13 (11/16) | P76: N/A | Q76: N/A | R76: 7 | S76: 25.5 | T76: 7000 | U76: 9.0/10 | V76: • Spacious passenger and cargo room • Commanding elevated driving position • Confidence-inspiring all-weather grip | W76: • Higher center of gravity than sedans • Fuel consumption under heavy load • Less engaging steering feel | X76: A highly versatile full-size performance suv that delivers generous space, modern safety tech, and daily utility. | Y76: https://hips.hearstapps.com/hmg-prod/images/2026-cadillac-escalade.jpg | Z76: https://www.caranddriver.com/cadillac/escalade | AA76: Car and Driver Editors' Choice
A77: 2026 | B77: Cadillac | C77: Escalade IQ | D77: Luxury 1 AWD | E77: Full-Size Ultra EV SUV | F77: Electric | G77: 129990 | H77: 750 | I77: 785 | J77: Dual Ultium Electric Motors | K77: N/A | L77: 0 | M77: 1-Speed Direct | N77: eAWD | O77: 59 MPGe | P77: 460 | Q77: 215 | R77: 7 | S77: 23.7 | T77: 8000 | U77: 9.0/10 | V77: • Silent, instantaneous acceleration • Low center of gravity enhances stability • Zero tailpipe emissions | W77: • Highway range drops at sustained speed • Public charging network variability • Pricier initial purchase cost | X77: A compelling electric entry in the full-size ultra ev suv segment offering smooth power delivery and advanced tech. | Y77: https://hips.hearstapps.com/hmg-prod/images/2026-cadillac-escalade-iq.jpg | Z77: https://www.caranddriver.com/cadillac/escalade-iq | AA77: Car and Driver Buyer's Guide
A78: 2026 | B78: Cadillac | C78: Celestiq | D78: Bespoke EV | E78: Ultra-Luxury Flagship Sedan | F78: Electric | G78: 340000 | H78: 600 | I78: 640 | J78: Dual Ultium Motors | K78: N/A | L78: 0 | M78: 1-Speed Direct | N78: AWD | O78: 80 MPGe (Est) | P78: 300 | Q78: 111 | R78: 4 | S78: 18 | T78: N/A | U78: 9.5/10 | V78: • Silent, instantaneous acceleration • Low center of gravity enhances stability • Zero tailpipe emissions | W78: • Highway range drops at sustained speed • Public charging network variability • Pricier initial purchase cost | X78: A compelling electric entry in the ultra-luxury flagship sedan segment offering smooth power delivery and advanced tech. | Y78: https://hips.hearstapps.com/hmg-prod/images/2026-cadillac-celestiq.jpg | Z78: https://www.caranddriver.com/cadillac/celestiq | AA78: Car and Driver First Look
A79: 2026 | B79: Chevrolet | C79: Trax | D79: ACTIV FWD | E79: Subcompact Crossover | F79: Gasoline | G79: 25395 | H79: 137 | I79: 162 | J79: 1.2L Turbo I3 | K79: 1.2 | L79: 3 | M79: 6-Speed Auto | N79: FWD | O79: 30 (28/32) | P79: N/A | Q79: N/A | R79: 5 | S79: 25.6 | T79: N/A | U79: 10/10 | V79: • Spacious passenger and cargo room • Commanding elevated driving position • Confidence-inspiring all-weather grip | W79: • Higher center of gravity than sedans • Fuel consumption under heavy load • Less engaging steering feel | X79: A highly versatile subcompact crossover that delivers generous space, modern safety tech, and daily utility. | Y79: https://hips.hearstapps.com/hmg-prod/images/2026-chevrolet-trax.jpg | Z79: https://www.caranddriver.com/chevrolet/trax | AA79: Car and Driver 10Best Winner
A80: 2026 | B80: Chevrolet | C80: Trailblazer | D80: RS AWD | E80: Subcompact Crossover | F80: Gasoline | G80: 31000 | H80: 155 | I80: 174 | J80: 1.3L Turbo I3 | K80: 1.3 | L80: 3 | M80: 9-Speed Auto | N80: AWD | O80: 27 (26/29) | P80: N/A | Q80: N/A | R80: 5 | S80: 25.3 | T80: 1000 | U80: 7.5/10 | V80: • Spacious passenger and cargo room • Commanding elevated driving position • Confidence-inspiring all-weather grip | W80: • Higher center of gravity than sedans • Fuel consumption under heavy load • Less engaging steering feel | X80: A highly versatile subcompact crossover that delivers generous space, modern safety tech, and daily utility. | Y80: https://hips.hearstapps.com/hmg-prod/images/2026-chevrolet-trailblazer.jpg | Z80: https://www.caranddriver.com/chevrolet/trailblazer | AA80: Car and Driver Buyer's Guide
A81: 2026 | B81: Chevrolet | C81: Equinox | D81: ACTIV AWD | E81: Compact Crossover | F81: Gasoline | G81: 35000 | H81: 175 | I81: 203 | J81: 1.5L Turbo I4 | K81: 1.5 | L81: 4 | M81: 8-Speed Auto | N81: AWD | O81: 26 (24/29) | P81: N/A | Q81: N/A | R81: 5 | S81: 29.8 | T81: 1500 | U81: 8.0/10 | V81: • Spacious passenger and cargo room • Commanding elevated driving position • Confidence-inspiring all-weather grip | W81: • Higher center of gravity than sedans • Fuel consumption under heavy load • Less engaging steering feel | X81: A highly versatile compact crossover that delivers generous space, modern safety tech, and daily utility. | Y81: https://hips.hearstapps.com/hmg-prod/images/2026-chevrolet-equinox.jpg | Z81: https://www.caranddriver.com/chevrolet/equinox | AA81: Car and Driver Buyer's Guide
A82: 2026 | B82: Chevrolet | C82: Equinox EV | D82: LT AWD | E82: Compact Electric SUV | F82: Electric | G82: 36295 | H82: 288 | I82: 333 | J82: Dual Ultium Motors | K82: N/A | L82: 0 | M82: 1-Speed Direct | N82: eAWD | O82: 96 MPGe | P82: 285 | Q82: 85 | R82: 5 | S82: 26.4 | T82: 1500 | U82: 9.0/10 | V82: • Silent, instantaneous acceleration • Low center of gravity enhances stability • Zero tailpipe emissions | W82: • Highway range drops at sustained speed • Public charging network variability • Pricier initial purchase cost | X82: A compelling electric entry in the compact electric suv segment offering smooth power delivery and advanced tech. | Y82: https://hips.hearstapps.com/hmg-prod/images/2026-chevrolet-equinox-ev.jpg | Z82: https://www.caranddriver.com/chevrolet/equinox-ev | AA82: Car and Driver Buyer's Guide
A83: 2026 | B83: Chevrolet | C83: Blazer | D83: RS AWD | E83: Mid-Size Crossover | F83: Gasoline | G83: 46000 | H83: 308 | I83: 270 | J83: 3.6L V6 | K83: 3.6 | L83: 6 | M83: 9-Speed Auto | N83: AWD | O83: 21 (19/26) | P83: N/A | Q83: N/A | R83: 5 | S83: 30.5 | T83: 4500 | U83: 7.5/10 | V83: • Spacious passenger and cargo room • Commanding elevated driving position • Confidence-inspiring all-weather grip | W83: • Higher center of gravity than sedans • Fuel consumption under heavy load • Less engaging steering feel | X83: A highly versatile mid-size crossover that delivers generous space, modern safety tech, and daily utility. | Y83: https://hips.hearstapps.com/hmg-prod/images/2026-chevrolet-blazer.jpg | Z83: https://www.caranddriver.com/chevrolet/blazer | AA83: Car and Driver Buyer's Guide
A84: 2026 | B84: Chevrolet | C84: Blazer EV | D84: SS AWD | E84: Performance EV SUV | F84: Electric | G84: 66000 | H84: 557 | I84: 648 | J84: Dual Ultium Motors | K84: N/A | L84: 0 | M84: 1-Speed Direct | N84: AWD | O84: 88 MPGe | P84: 290 | Q84: 85 | R84: 5 | S84: 25.5 | T84: 1500 | U84: 8.5/10 | V84: • Silent, instantaneous acceleration • Low center of gravity enhances stability • Zero tailpipe emissions | W84: • Highway range drops at sustained speed • Public charging network variability • Pricier initial purchase cost | X84: A compelling electric entry in the performance ev suv segment offering smooth power delivery and advanced tech. | Y84: https://hips.hearstapps.com/hmg-prod/images/2026-chevrolet-blazer-ev.jpg | Z84: https://www.caranddriver.com/chevrolet/blazer-ev | AA84: Car and Driver Tested
A85: 2026 | B85: Chevrolet | C85: Traverse | D85: Z71 AWD | E85: 3-Row Mid-Size SUV | F85: Gasoline | G85: 48000 | H85: 328 | I85: 326 | J85: 2.5L Turbo I4 | K85: 2.5 | L85: 4 | M85: 8-Speed Auto | N85: Twin-Clutch AWD | O85: 21 (19/24) | P85: N/A | Q85: N/A | R85: 8 | S85: 22.9 | T85: 5000 | U85: 8.5/10 | V85: • Spacious passenger and cargo room • Commanding elevated driving position • Confidence-inspiring all-weather grip | W85: • Higher center of gravity than sedans • Fuel consumption under heavy load • Less engaging steering feel | X85: A highly versatile 3-row mid-size suv that delivers generous space, modern safety tech, and daily utility. | Y85: https://hips.hearstapps.com/hmg-prod/images/2026-chevrolet-traverse.jpg | Z85: https://www.caranddriver.com/chevrolet/traverse | AA85: Car and Driver Buyer's Guide
A86: 2026 | B86: Chevrolet | C86: Tahoe | D86: High Country 4WD | E86: Full-Size 3-Row SUV | F86: Gasoline | G86: 80195 | H86: 420 | I86: 460 | J86: 6.2L EcoTec3 V8 | K86: 6.2 | L86: 8 | M86: 10-Speed Auto | N86: 4WD | O86: 16 (14/18) | P86: N/A | Q86: N/A | R86: 8 | S86: 25.5 | T86: 8300 | U86: 10/10 | V86: • Spacious passenger and cargo room • Commanding elevated driving position • Confidence-inspiring all-weather grip | W86: • Higher center of gravity than sedans • Fuel consumption under heavy load • Less engaging steering feel | X86: A highly versatile full-size 3-row suv that delivers generous space, modern safety tech, and daily utility. | Y86: https://hips.hearstapps.com/hmg-prod/images/2026-chevrolet-tahoe.jpg | Z86: https://www.caranddriver.com/chevrolet/tahoe | AA86: Car and Driver 10Best Winner
A87: 2026 | B87: Chevrolet | C87: Suburban | D87: High Country 4WD | E87: Extended Full-Size SUV | F87: Gasoline | G87: 83195 | H87: 420 | I87: 460 | J87: 6.2L EcoTec3 V8 | K87: 6.2 | L87: 8 | M87: 10-Speed Auto | N87: 4WD | O87: 16 (14/18) | P87: N/A | Q87: N/A | R87: 8 | S87: 41.5 | T87: 8200 | U87: 10/10 | V87: • Spacious passenger and cargo room • Commanding elevated driving position • Confidence-inspiring all-weather grip | W87: • Higher center of gravity than sedans • Fuel consumption under heavy load • Less engaging steering feel | X87: A highly versatile extended full-size suv that delivers generous space, modern safety tech, and daily utility. | Y87: https://hips.hearstapps.com/hmg-prod/images/2026-chevrolet-suburban.jpg | Z87: https://www.caranddriver.com/chevrolet/suburban | AA87: Car and Driver 10Best Winner
A88: 2026 | B88: Chevrolet | C88: Colorado | D88: ZR2 Crew Cab | E88: Mid-Size Off-Road Truck | F88: Gasoline | G88: 49800 | H88: 310 | I88: 430 | J88: 2.7L TurboMax High-Output I4 | K88: 2.7 | L88: 4 | M88: 8-Speed Auto | N88: 4WD | O88: 18 (17/19) | P88: N/A | Q88: N/A | R88: 5 | S88: 41.9 | T88: 6000 | U88: 9.5/10 | V88: • Robust payload and towing capabilities • Durable bed and tailgate features • High ground clearance | W88: • Stiffer unladen ride quality • Challenging to park in urban garages • Higher fuel costs | X88: A capable and rugged mid-size off-road truck designed for serious work duty, hauling, and outdoor recreation. | Y88: https://hips.hearstapps.com/hmg-prod/images/2026-chevrolet-colorado.jpg | Z88: https://www.caranddriver.com/chevrolet/colorado | AA88: Car and Driver Editors' Choice
A89: 2026 | B89: Chevrolet | C89: Silverado 1500 | D89: LT Trail Boss Crew Cab | E89: Full-Size Pickup | F89: Gasoline | G89: 60195 | H89: 420 | I89: 460 | J89: 6.2L EcoTec3 V8 | K89: 6.2 | L89: 8 | M89: 10-Speed Auto | N89: 4WD | O89: 16 (14/18) | P89: N/A | Q89: N/A | R89: 5 | S89: 62.9 | T89: 13300 | U89: 8.5/10 | V89: • Class-leading towing and hauling brawn • Palatial crew cab seating and storage • Intuitive cabin switchgear | W89: • Large exterior dimensions in tight parking • Thirsty when loaded • Top trims push into luxury car pricing | X89: The backbone of American transportation, offering effortless hauling capability and luxury cabin appointments. | Y89: https://hips.hearstapps.com/hmg-prod/images/2026-chevrolet-silverado-1500.jpg | Z89: https://www.caranddriver.com/chevrolet/silverado-1500 | AA89: Car and Driver Buyer's Guide
A90: 2026 | B90: Chevrolet | C90: Silverado EV | D90: RST First Edition | E90: Full-Size EV Truck | F90: Electric | G90: 96495 | H90: 754 | I90: 785 | J90: Dual Ultium Electric Motors | K90: N/A | L90: 0 | M90: 1-Speed Direct | N90: eAWD | O90: 67 MPGe | P90: 440 | Q90: 205 | R90: 5 | S90: 57.7 | T90: 10000 | U90: 9.0/10 | V90: • Massive instant electric torque • Innovative front frunk storage • Vehicle-to-home export power | W90: • Significant range reduction while towing • DC fast-charging infrastructure bottlenecks • Heavy curb weight | X90: Revolutionary electric utility that transforms work sites and family travel when towing demands are modest. | Y90: https://hips.hearstapps.com/hmg-prod/images/2026-chevrolet-silverado-ev.jpg | Z90: https://www.caranddriver.com/chevrolet/silverado-ev | AA90: Car and Driver Tested
A91: 2026 | B91: Chevrolet | C91: Silverado 2500HD | D91: High Country Duramax | E91: Heavy-Duty Truck | F91: Gasoline | G91: 82000 | H91: 470 | I91: 975 | J91: 6.6L Duramax Turbo-Diesel V8 | K91: 6.6 | L91: 8 | M91: 10-Speed Allison Auto | N91: 4WD | O91: 15 (Est) | P91: N/A | Q91: N/A | R91: 5 | S91: 69.5 | T91: 22500 | U91: 8.5/10 | V91: • Class-leading towing and hauling brawn • Palatial crew cab seating and storage • Intuitive cabin switchgear | W91: • Large exterior dimensions in tight parking • Thirsty when loaded • Top trims push into luxury car pricing | X91: The backbone of American transportation, offering effortless hauling capability and luxury cabin appointments. | Y91: https://hips.hearstapps.com/hmg-prod/images/2026-chevrolet-silverado-2500hd.jpg | Z91: https://www.caranddriver.com/chevrolet/silverado-2500hd | AA91: Car and Driver Buyer's Guide
A92: 2026 | B92: Chevrolet | C92: Corvette | D92: Stingray 1LT Coupe | E92: Sports Car | F92: Gasoline | G92: 70000 | H92: 495 | I92: 470 | J92: 6.2L LT2 V8 | K92: 6.2 | L92: 8 | M92: 8-Speed Dual-Clutch | N92: RWD | O92: 19 (16/24) | P92: N/A | Q92: N/A | R92: 2 | S92: 12.6 | T92: N/A | U92: 10/10 | V92: • Exotic mid-engine balance and poise • Everyday usability and luggage trunks • Bargain supercar speed | W92: • No manual gearbox offered • Intimidating cockpit wall of buttons • Compromised rearward view | X92: The C8 Stingray remains one of the finest sports car achievements in modern automotive history. | Y92: https://hips.hearstapps.com/hmg-prod/images/2026-chevrolet-corvette.jpg | Z92: https://www.caranddriver.com/chevrolet/corvette | AA92: Car and Driver 10Best Winner
A93: 2026 | B93: Chevrolet | C93: Corvette | D93: E-Ray 1LZ AWD | E93: Hybrid Supercar | F93: Gas-Electric Hybrid | G93: 106595 | H93: 655 | I93: 595 | J93: 6.2L LT2 V8 + Front Motor | K93: 6.2 | L93: 8 | M93: 8-Speed Dual-Clutch | N93: eAWD | O93: 19 (16/24) | P93: N/A | Q93: 1.9 | R93: 2 | S93: 12.6 | T93: N/A | U93: 10/10 | V93: • Blistering all-weather launch grip • Stealth mode EV cruising capability • GT touring ride comfort | W93: • Heavier than standard Stingray • No manual option • High price tier | X93: The Corvette E-Ray blends instant electric all-wheel-drive traction with traditional pushrod V8 thunder. | Y93: https://hips.hearstapps.com/hmg-prod/images/2026-chevrolet-corvette.jpg | Z93: https://www.caranddriver.com/chevrolet/corvette-e-ray | AA93: Car and Driver 10Best
A94: 2026 | B94: Chevrolet | C94: Corvette | D94: Z06 1LZ Coupe | E94: Supercar | F94: Gasoline | G94: 114395 | H94: 670 | I94: 460 | J94: 5.5L Flat-Plane LT6 V8 | K94: 5.5 | L94: 8 | M94: 8-Speed Dual-Clutch | N94: RWD | O94: 15 (12/19) | P94: N/A | Q94: N/A | R94: 2 | S94: 12.6 | T94: N/A | U94: 10/10 | V94: • Exotic 8600-rpm flat-plane V8 scream • Supercar grip and telepathic steering • Unbeatable exotic value | W94: • Fierce fuel consumption • Firm ride around town • Limited luggage storage | X94: A track-focused masterstroke whose naturally aspirated engine is one of the greatest combustion motors ever created. | Y94: https://hips.hearstapps.com/hmg-prod/images/2026-chevrolet-corvette.jpg | Z94: https://www.caranddriver.com/chevrolet/corvette-z06 | AA94: Car and Driver 10Best Winner
A95: 2026 | B95: Chevrolet | C95: Corvette | D95: ZR1 Coupe | E95: Flagship Hypercar | F95: Gasoline | G95: 180000 | H95: 1064 | I95: 828 | J95: 5.5L Twin-Turbo Flat-Plane LT7 V8 | K95: 5.5 | L95: 8 | M95: 8-Speed Dual-Clutch | N95: RWD | O95: 14 (11/17 Est) | P95: N/A | Q95: N/A | R95: 2 | S95: 12.6 | T95: N/A | U95: 10/10 | V95: • Astounding 1064-hp twin-turbo V8 • True hypercar-crushing performance • Dramatic aero package | W95: • Expect massive dealer markups • Tire appetite under track use • Stiff ride on rough roads | X95: The Corvette ZR1 takes American supercar performance into uncharted hypercar territory with four-digit horsepower. | Y95: https://hips.hearstapps.com/hmg-prod/images/2026-chevrolet-corvette.jpg | Z95: https://www.caranddriver.com/chevrolet/corvette-zr1 | AA95: Car and Driver Deep Dive
A96: 2026 | B96: Chrysler | C96: Pacifica | D96: Pinnacle Hybrid | E96: Plug-in Hybrid Minivan | F96: PHEV | G96: 61000 | H96: 260 | I96: 235 | J96: 3.6L V6 + Dual Motors | K96: 3.6 | L96: 6 | M96: eFlite EVT | N96: FWD | O96: 82 MPGe / 30 Comb | P96: 32 | Q96: 16 | R96: 7 | S96: 32.3 | T96: 3600 | U96: 9.0/10 | V96: • Superb real-world fuel economy • Smooth electric-gas power handover • No range anxiety on long trips | W96: • Added curb weight from battery packs • Slightly compromised cargo space • eCVT engine flare during passing | X96: A finely engineered phev plug-in hybrid minivan striking the optimal balance between high efficiency and long-distance practicality. | Y96: https://hips.hearstapps.com/hmg-prod/images/2026-chrysler-pacifica.jpg | Z96: https://www.caranddriver.com/chrysler/pacifica | AA96: Car and Driver Editors' Choice
A97: 2026 | B97: Chrysler | C97: Voyager | D97: LX | E97: Budget Minivan | F97: Gasoline | G97: 41000 | H97: 287 | I97: 262 | J97: 3.6L Pentastar V6 | K97: 3.6 | L97: 6 | M97: 9-Speed Auto | N97: FWD | O97: 22 (19/28) | P97: N/A | Q97: N/A | R97: 7 | S97: 32.3 | T97: 3600 | U97: 7.5/10 | V97: • Refined performance and chassis poise • Comfortable ergonomic cabin • Comprehensive safety suite | W97: • Firm ride on optional large wheels • Option packages add up quickly • Infotainment learning curve | X97: A solid, well-rounded contender in the US budget minivan class with competitive dynamics. | Y97: https://hips.hearstapps.com/hmg-prod/images/2026-chrysler-voyager.jpg | Z97: https://www.caranddriver.com/chrysler/voyager | AA97: Car and Driver Buyer's Guide
A98: 2026 | B98: Dodge | C98: Hornet | D98: R/T Plus EAWD | E98: Compact Performance Crossover | F98: PHEV | G98: 48000 | H98: 288 | I98: 383 | J98: 1.3L Turbo I4 + Motor | K98: 1.3 | L98: 4 | M98: 6-Speed Auto | N98: AWD | O98: 77 MPGe / 29 Comb | P98: 32 | Q98: 15.5 | R98: 5 | S98: 27 | T98: 2000 | U98: 8.0/10 | V98: • Superb real-world fuel economy • Smooth electric-gas power handover • No range anxiety on long trips | W98: • Added curb weight from battery packs • Slightly compromised cargo space • eCVT engine flare during passing | X98: A finely engineered phev compact performance crossover striking the optimal balance between high efficiency and long-distance practicality. | Y98: https://hips.hearstapps.com/hmg-prod/images/2026-dodge-hornet.jpg | Z98: https://www.caranddriver.com/dodge/hornet | AA98: Car and Driver Buyer's Guide
A99: 2026 | B99: Dodge | C99: Charger Daytona | D99: R/T Stage 1 | E99: 2-Door Muscle EV | F99: Electric | G99: 61590 | H99: 496 | I99: 404 | J99: Dual 250kW Electric Motors | K99: N/A | L99: 0 | M99: 1-Speed Direct | N99: AWD | O99: 82 MPGe | P99: 317 | Q99: 100.5 | R99: 5 | S99: 22.8 | T99: N/A | U99: 8.5/10 | V99: • Silent, instantaneous acceleration • Low center of gravity enhances stability • Zero tailpipe emissions | W99: • Highway range drops at sustained speed • Public charging network variability • Pricier initial purchase cost | X99: A compelling electric entry in the 2-door muscle ev segment offering smooth power delivery and advanced tech. | Y99: https://hips.hearstapps.com/hmg-prod/images/2026-dodge-charger-daytona.jpg | Z99: https://www.caranddriver.com/dodge/charger-daytona | AA99: Car and Driver First Drive
A100: 2026 | B100: Dodge | C100: Charger Daytona | D100: Scat Pack Stage 2 | E100: 2-Door Muscle EV | F100: Electric | G100: 75185 | H100: 670 | I100: 627 | J100: Dual 335kW Motors | K100: N/A | L100: 0 | M100: 1-Speed Direct | N100: AWD | O100: 76 MPGe | P100: 260 | Q100: 100.5 | R100: 5 | S100: 22.8 | T100: N/A | U100: 8.5/10 | V100: • Silent, instantaneous acceleration • Low center of gravity enhances stability • Zero tailpipe emissions | W100: • Highway range drops at sustained speed • Public charging network variability • Pricier initial purchase cost | X100: A compelling electric entry in the 2-door muscle ev segment offering smooth power delivery and advanced tech. | Y100: https://hips.hearstapps.com/hmg-prod/images/2026-dodge-charger-daytona.jpg | Z100: https://www.caranddriver.com/dodge/charger-daytona | AA100: Car and Driver First Drive
...

Sheet Executive Summary & Analytics
A1: US Automotive Market Master Analytics & Segment Distribution
A3: Market Overview KPI Indicators | D3: Powertrain Propulsion Mix
A4: Indicator Metric | B4: Aggregate Value | D4: Powertrain Classification | E4: Vehicle Count
A5: Total Documented US Vehicle Models | B5: =COUNTA('Master 2026-2027 US Catalog'!A4:A458) | D5: Gasoline | E5: =COUNTIF('Master 2026-2027 US Catalog'!F4:F458, "Gasoline")
A6: Average Vehicle MSRP | B6: =AVERAGE('Master 2026-2027 US Catalog'!G4:G458) | D6: Electric | E6: =COUNTIF('Master 2026-2027 US Catalog'!F4:F458, "Electric")
A7: Minimum Vehicle MSRP | B7: =MIN('Master 2026-2027 US Catalog'!G4:G458) | D7: Gas-Electric Hybrid | E7: =COUNTIF('Master 2026-2027 US Catalog'!F4:F458, "Gas-Electric Hybrid")
A8: Maximum Vehicle MSRP | B8: =MAX('Master 2026-2027 US Catalog'!G4:G458) | D8: PHEV | E8: =COUNTIF('Master 2026-2027 US Catalog'!F4:F458, "PHEV")
A9: Average Horsepower Output | B9: =AVERAGE('Master 2026-2027 US Catalog'!H4:H458) | D9: Mild Hybrid | E9: =COUNTIF('Master 2026-2027 US Catalog'!F4:F458, "Mild Hybrid")
A10: Maximum Horsepower Output | B10: =MAX('Master 2026-2027 US Catalog'!H4:H458)
A11: Average Torque Output | B11: =AVERAGE('Master 2026-2027 US Catalog'!I4:I458)
A14: Manufacturer Representation
A15: Brand / Make | B15: Models Cataloged
A16: Acura | B16: =COUNTIF('Master 2026-2027 US Catalog'!B4:B458, "Acura")
A17: Alfa Romeo | B17: =COUNTIF('Master 2026-2027 US Catalog'!B4:B458, "Alfa Romeo")
A18: Aston Martin | B18: =COUNTIF('Master 2026-2027 US Catalog'!B4:B458, "Aston Martin")
A19: Audi | B19: =COUNTIF('Master 2026-2027 US Catalog'!B4:B458, "Audi")
A20: BMW | B20: =COUNTIF('Master 2026-2027 US Catalog'!B4:B458, "BMW")
A21: Bentley | B21: =COUNTIF('Master 2026-2027 US Catalog'!B4:B458, "Bentley")
A22: Buick | B22: =COUNTIF('Master 2026-2027 US Catalog'!B4:B458, "Buick")
A23: Cadillac | B23: =COUNTIF('Master 2026-2027 US Catalog'!B4:B458, "Cadillac")
A24: Chevrolet | B24: =COUNTIF('Master 2026-2027 US Catalog'!B4:B458, "Chevrolet")
A25: Chrysler | B25: =COUNTIF('Master 2026-2027 US Catalog'!B4:B458, "Chrysler")
A26: Dodge | B26: =COUNTIF('Master 2026-2027 US Catalog'!B4:B458, "Dodge")
A27: Ferrari | B27: =COUNTIF('Master 2026-2027 US Catalog'!B4:B458, "Ferrari")
A28: Fiat | B28: =COUNTIF('Master 2026-2027 US Catalog'!B4:B458, "Fiat")
A29: Ford | B29: =COUNTIF('Master 2026-2027 US Catalog'!B4:B458, "Ford")
A30: GMC | B30: =COUNTIF('Master 2026-2027 US Catalog'!B4:B458, "GMC")
A31: Genesis | B31: =COUNTIF('Master 2026-2027 US Catalog'!B4:B458, "Genesis")
A32: Honda | B32: =COUNTIF('Master 2026-2027 US Catalog'!B4:B458, "Honda")
A33: Hyundai | B33: =COUNTIF('Master 2026-2027 US Catalog'!B4:B458, "Hyundai")
A34: Infiniti | B34: =COUNTIF('Master 2026-2027 US Catalog'!B4:B458, "Infiniti")
A35: Jaguar | B35: =COUNTIF('Master 2026-2027 US Catalog'!B4:B458, "Jaguar")
A36: Jeep | B36: =COUNTIF('Master 2026-2027 US Catalog'!B4:B458, "Jeep")
A37: Kia | B37: =COUNTIF('Master 2026-2027 US Catalog'!B4:B458, "Kia")
A38: Lamborghini | B38: =COUNTIF('Master 2026-2027 US Catalog'!B4:B458, "Lamborghini")
A39: Land Rover | B39: =COUNTIF('Master 2026-2027 US Catalog'!B4:B458, "Land Rover")
A40: Lexus | B40: =COUNTIF('Master 2026-2027 US Catalog'!B4:B458, "Lexus")
A41: Lincoln | B41: =COUNTIF('Master 2026-2027 US Catalog'!B4:B458, "Lincoln")
A42: Lotus | B42: =COUNTIF('Master 2026-2027 US Catalog'!B4:B458, "Lotus")
A43: Lucid | B43: =COUNTIF('Master 2026-2027 US Catalog'!B4:B458, "Lucid")
A44: MINI | B44: =COUNTIF('Master 2026-2027 US Catalog'!B4:B458, "MINI")
A45: Maserati | B45: =COUNTIF('Master 2026-2027 US Catalog'!B4:B458, "Maserati")
A46: Mazda | B46: =COUNTIF('Master 2026-2027 US Catalog'!B4:B458, "Mazda")
A47: McLaren | B47: =COUNTIF('Master 2026-2027 US Catalog'!B4:B458, "McLaren")
A48: Mercedes-Benz | B48: =COUNTIF('Master 2026-2027 US Catalog'!B4:B458, "Mercedes-Benz")
A49: Mitsubishi | B49: =COUNTIF('Master 2026-2027 US Catalog'!B4:B458, "Mitsubishi")
A50: Nissan | B50: =COUNTIF('Master 2026-2027 US Catalog'!B4:B458, "Nissan")
A51: Polestar | B51: =COUNTIF('Master 2026-2027 US Catalog'!B4:B458, "Polestar")
A52: Porsche | B52: =COUNTIF('Master 2026-2027 US Catalog'!B4:B458, "Porsche")
A53: Ram | B53: =COUNTIF('Master 2026-2027 US Catalog'!B4:B458, "Ram")
A54: Rivian | B54: =COUNTIF('Master 2026-2027 US Catalog'!B4:B458, "Rivian")
A55: Rolls-Royce | B55: =COUNTIF('Master 2026-2027 US Catalog'!B4:B458, "Rolls-Royce")
A56: Scout | B56: =COUNTIF('Master 2026-2027 US Catalog'!B4:B458, "Scout")
A57: Subaru | B57: =COUNTIF('Master 2026-2027 US Catalog'!B4:B458, "Subaru")
A58: Tesla | B58: =COUNTIF('Master 2026-2027 US Catalog'!B4:B458, "Tesla")
A59: Toyota | B59: =COUNTIF('Master 2026-2027 US Catalog'!B4:B458, "Toyota")
A60: VinFast | B60: =COUNTIF('Master 2026-2027 US Catalog'!B4:B458, "VinFast")
A61: Volkswagen | B61: =COUNTIF('Master 2026-2027 US Catalog'!B4:B458, "Volkswagen")
A62: Volvo | B62: =COUNTIF('Master 2026-2027 US Catalog'!B4:B458, "Volvo")
